{
    "posts": [
        {
            "uuid": "2f31ea8f-d8a2-475d-925b-0aade88bb9c3",
            "author": "htman.dung",
            "content": "Ch\u00e0o c\u00e1c b\u00e1c, Sau khi ra m\u1eaft t\u1eadp 1Kh\u00f4ng \u0111\u01b0\u1ee3c d\u1eabn link topic c\u0169 v\u00e0o top n\u00e0y!\u0111\u01b0\u1ee3c c\u00e1c b\u00e1c h\u01b0\u1edfng \u1ee9ng, em xin ti\u1ebfp t\u1ee5c t\u1eadp 2. Ruby v\u00e0 em g\u1eb7p anh ch\u00e0ng n\u00e0y \u1edf 1 swing club (b\u00ean n\u00e0y m\u1ea5y club sex \u0111\u01b0\u1ee3c cho ph\u00e9p ho\u1ea1t \u0111\u1ed9ng c\u00f4ng khai c\u00e1c b\u00e1c \u1ea1). Anh n\u00e0y g\u1ed1c M\u1ef9 Latin, \u0111\u1eb9p trai, da ng\u0103m \u0111en n\u00ean Ruby m\u00ea ng\u1eadp t\u1ee9c. Sau khi n\u00f3i chuy\u1ec7n th\u1ea5y h\u1ee3p th\u00ec em quy\u1ebft \u0111\u1ecbnh r\u1ee7 v\u1ec1 nh\u00e0 h\u00e0nh s\u1ef1, v\u00ec \u1edf club l\u00fac \u0111\u00f3 h\u01a1i \u0111\u00f4ng. V\u1ec1 t\u1edbi nh\u00e0, em \u0111i c\u1ea5t xe v\u00f4 t\u1edbi ph\u00f2ng th\u00ec \u0111\u00e3 th\u1ea5y \u0111\u0129 d\u00e2m nh\u00e0 em b\u1ecb l\u1ed9t tr\u1ea7n v\u00e0 h\u00f4n h\u00edt kh\u1eafp n\u01a1i. Anh ch\u00e0ng n\u00e0y \u0111\u00fang l\u00e0 r\u1ea5t c\u01a1 b\u1eafp. Nh\u00ecn 2 m\u00e0u da t\u01b0\u01a1ng ph\u1ea3n r\u1ea5t k\u00edch th\u00edch c\u00e1c b\u00e1c \u1ea1. Sau khi h\u00f4n h\u00edt s\u1edd m\u00f3 1 h\u1ed3i th\u00ec Ruby nh\u00e0 em ghi\u1ec1n chu\u1ed1i ch\u1ecbu h\u1ebft n\u1ed5i n\u00ean n\u0103ng n\u1ec9 b\u1ea1n t\u00ecnh \u0111\u00fat chu\u1ed1i v\u00e0o. Anh n\u00e0y c\u1ee9 v\u1eeba \u0111\u00e2m v\u1eeba khen v\u00fa \u00e1 \u0111\u00f4ng nh\u1ed3i r\u1ea5t \u0111\u00e3 Ruby c\u1ee9 r\u00ean \u01b0 \u1eed l\u00fac \u0111\u01b0\u1ee3c \u0111\u00e2m. \u0110\u00e2y l\u00e0 l\u00fac Ruby n\u1eb1m xu\u1ed1ng v\u00e0 gi\u01a1 ch\u00e2n l\u00ean khoe l\u1ed3n \u0111\u1ec3 \u0111\u01b0\u1ee3c chu\u1ed1i T\u00e2y \u0111\u1ecbt. T\u1ea5m n\u00e0y l\u00e0 \u0111\u00e2m l\u00fat c\u00e1n. Mong c\u00e1c b\u00e1c quay tay vui v\u1ebb",
            "content_html": "Ch\u00e0o c\u00e1c b\u00e1c,<br><br>Sau khi ra m\u1eaft t\u1eadp 1<br><span style=\"color: #b30000\">Kh\u00f4ng \u0111\u01b0\u1ee3c d\u1eabn link topic c\u0169 v\u00e0o top n\u00e0y!<\/span><br>\u0111\u01b0\u1ee3c c\u00e1c b\u00e1c h\u01b0\u1edfng \u1ee9ng, em xin ti\u1ebfp t\u1ee5c t\u1eadp 2.<br><br>Ruby v\u00e0 em g\u1eb7p anh ch\u00e0ng n\u00e0y \u1edf 1 swing club (b\u00ean n\u00e0y m\u1ea5y club sex \u0111\u01b0\u1ee3c cho ph\u00e9p ho\u1ea1t \u0111\u1ed9ng c\u00f4ng khai c\u00e1c b\u00e1c \u1ea1). Anh n\u00e0y g\u1ed1c M\u1ef9 Latin, \u0111\u1eb9p trai, da ng\u0103m \u0111en n\u00ean Ruby m\u00ea ng\u1eadp t\u1ee9c. Sau khi n\u00f3i chuy\u1ec7n th\u1ea5y h\u1ee3p th\u00ec em quy\u1ebft \u0111\u1ecbnh r\u1ee7 v\u1ec1 nh\u00e0 h\u00e0nh s\u1ef1, v\u00ec \u1edf club l\u00fac \u0111\u00f3 h\u01a1i \u0111\u00f4ng.<br><br>V\u1ec1 t\u1edbi nh\u00e0, em \u0111i c\u1ea5t xe v\u00f4 t\u1edbi ph\u00f2ng th\u00ec \u0111\u00e3 th\u1ea5y \u0111\u0129 d\u00e2m nh\u00e0 em b\u1ecb l\u1ed9t tr\u1ea7n v\u00e0 h\u00f4n h\u00edt kh\u1eafp n\u01a1i.<br><br> <script class=\"js-extraPhrases\" type=\"application\/json\"> { \"lightbox_close\": \"Close\", \"lightbox_next\": \"Next\", \"lightbox_previous\": \"Previous\", \"lightbox_error\": \"The requested content cannot be loaded. Please try again later.\", \"lightbox_start_slideshow\": \"Start slideshow\", \"lightbox_stop_slideshow\": \"Stop slideshow\", \"lightbox_full_screen\": \"Full screen\", \"lightbox_thumbnails\": \"Thumbnails\", \"lightbox_download\": \"Download\", \"lightbox_share\": \"Share\", \"lightbox_zoom\": \"Zoom\", \"lightbox_new_window\": \"New window\", \"lightbox_toggle_sidebar\": \"Toggle sidebar\" } <\/script> <div class=\"bbImageWrapper js-lbImage\" title=\"IMG_4612-2-12.jpg\" data-src=\"https:\/\/greenupload.com\/images\/2018\/11\/18\/IMG_4612-2-12.jpg\" data-lb-sidebar-href=\"\" data-lb-caption-extra-html=\"\" data-single-image=\"1\"> <img src=\"https:\/\/greenupload.com\/images\/2018\/11\/18\/IMG_4612-2-12.jpg\" data-url=\"https:\/\/greenupload.com\/images\/2018\/11\/18\/IMG_4612-2-12.jpg\" class=\"bbImage\" data-zoom-target=\"1\" style=\"\" alt=\"IMG_4612-2-12.jpg\" title=\"\" width=\"\" height=\"\" loading=\"lazy\"> <\/div> <br><br>Anh ch\u00e0ng n\u00e0y \u0111\u00fang l\u00e0 r\u1ea5t c\u01a1 b\u1eafp. Nh\u00ecn 2 m\u00e0u da t\u01b0\u01a1ng ph\u1ea3n r\u1ea5t k\u00edch th\u00edch c\u00e1c b\u00e1c \u1ea1. Sau khi h\u00f4n h\u00edt s\u1edd m\u00f3 1 h\u1ed3i th\u00ec Ruby nh\u00e0 em ghi\u1ec1n chu\u1ed1i ch\u1ecbu h\u1ebft n\u1ed5i n\u00ean n\u0103ng n\u1ec9 b\u1ea1n t\u00ecnh \u0111\u00fat chu\u1ed1i v\u00e0o.<br><br> <div class=\"bbImageWrapper js-lbImage\" title=\"IMG_4611-2-11.jpg\" data-src=\"https:\/\/greenupload.com\/images\/2018\/11\/18\/IMG_4611-2-11.jpg\" data-lb-sidebar-href=\"\" data-lb-caption-extra-html=\"\" data-single-image=\"1\"> <img src=\"https:\/\/greenupload.com\/images\/2018\/11\/18\/IMG_4611-2-11.jpg\" data-url=\"https:\/\/greenupload.com\/images\/2018\/11\/18\/IMG_4611-2-11.jpg\" class=\"bbImage\" data-zoom-target=\"1\" style=\"\" alt=\"IMG_4611-2-11.jpg\" title=\"\" width=\"\" height=\"\" loading=\"lazy\"> <\/div> <br><br>Anh n\u00e0y c\u1ee9 v\u1eeba \u0111\u00e2m v\u1eeba khen v\u00fa \u00e1 \u0111\u00f4ng nh\u1ed3i r\u1ea5t \u0111\u00e3<br><br> <div class=\"bbImageWrapper js-lbImage\" title=\"IMG_4610-2-10.jpg\" data-src=\"https:\/\/greenupload.com\/images\/2018\/11\/18\/IMG_4610-2-10.jpg\" data-lb-sidebar-href=\"\" data-lb-caption-extra-html=\"\" data-single-image=\"1\"> <img src=\"https:\/\/greenupload.com\/images\/2018\/11\/18\/IMG_4610-2-10.jpg\" data-url=\"https:\/\/greenupload.com\/images\/2018\/11\/18\/IMG_4610-2-10.jpg\" class=\"bbImage\" data-zoom-target=\"1\" style=\"\" alt=\"IMG_4610-2-10.jpg\" title=\"\" width=\"\" height=\"\" loading=\"lazy\"> <\/div> <br><br>Ruby c\u1ee9 r\u00ean \u01b0 \u1eed l\u00fac \u0111\u01b0\u1ee3c \u0111\u00e2m. \u0110\u00e2y l\u00e0 l\u00fac Ruby n\u1eb1m xu\u1ed1ng v\u00e0 gi\u01a1 ch\u00e2n l\u00ean khoe l\u1ed3n \u0111\u1ec3 \u0111\u01b0\u1ee3c chu\u1ed1i T\u00e2y \u0111\u1ecbt.<br><br> <div class=\"bbImageWrapper js-lbImage\" title=\"IMG_4606-2-8.jpg\" data-src=\"https:\/\/greenupload.com\/images\/2018\/11\/18\/IMG_4606-2-8.jpg\" data-lb-sidebar-href=\"\" data-lb-caption-extra-html=\"\" data-single-image=\"1\"> <img src=\"https:\/\/greenupload.com\/images\/2018\/11\/18\/IMG_4606-2-8.jpg\" data-url=\"https:\/\/greenupload.com\/images\/2018\/11\/18\/IMG_4606-2-8.jpg\" class=\"bbImage\" data-zoom-target=\"1\" style=\"\" alt=\"IMG_4606-2-8.jpg\" title=\"\" width=\"\" height=\"\" loading=\"lazy\"> <\/div> <br><br> <div class=\"bbImageWrapper js-lbImage\" title=\"IMG_4608-2-9.jpg\" data-src=\"https:\/\/greenupload.com\/images\/2018\/11\/18\/IMG_4608-2-9.jpg\" data-lb-sidebar-href=\"\" data-lb-caption-extra-html=\"\" data-single-image=\"1\"> <img src=\"https:\/\/greenupload.com\/images\/2018\/11\/18\/IMG_4608-2-9.jpg\" data-url=\"https:\/\/greenupload.com\/images\/2018\/11\/18\/IMG_4608-2-9.jpg\" class=\"bbImage\" data-zoom-target=\"1\" style=\"\" alt=\"IMG_4608-2-9.jpg\" title=\"\" width=\"\" height=\"\" loading=\"lazy\"> <\/div> <br><br>T\u1ea5m n\u00e0y l\u00e0 \u0111\u00e2m l\u00fat c\u00e1n.<br><br> <div class=\"bbImageWrapper js-lbImage\" title=\"IMG_4605-2-7.jpg\" data-src=\"https:\/\/greenupload.com\/images\/2018\/11\/18\/IMG_4605-2-7.jpg\" data-lb-sidebar-href=\"\" data-lb-caption-extra-html=\"\" data-single-image=\"1\"> <img src=\"https:\/\/greenupload.com\/images\/2018\/11\/18\/IMG_4605-2-7.jpg\" data-url=\"https:\/\/greenupload.com\/images\/2018\/11\/18\/IMG_4605-2-7.jpg\" class=\"bbImage\" data-zoom-target=\"1\" style=\"\" alt=\"IMG_4605-2-7.jpg\" title=\"\" width=\"\" height=\"\" loading=\"lazy\"> <\/div> <br><br>Mong c\u00e1c b\u00e1c quay tay vui v\u1ebb <img src=\"data:image\/gif;base64,R0lGODlhAQABAIAAAAAAAP\/\/\/yH5BAEAAAAALAAAAAABAAEAAAIBRAA7\" class=\"smilie smilie--sprite smilie--sprite8\" alt=\":D\" title=\"Big Grin :D\" loading=\"lazy\" data-shortname=\":D\">",
            "link_uuid": "d4b5919f-336d-4b2d-af98-9efc5dbf51a9",
            "post_id": "post-30473600",
            "status": "PROCESSED",
            "download_links_status": "PROCESSED_NO_LINKS",
            "type": "MAIN_POST",
            "total_image": "6",
            "created_at": "2021-06-19 16:23:40"
        },
        {
            "uuid": "a0536d8a-4a68-4e03-832e-64368e1afc4e",
            "author": "htman.dung",
            "content": "C\u1ea3m \u01a1n c\u00e1c b\u00e1c \u0111\u1ed3ng d\u00e2m \u0111\u00e3 \u1ee7ng h\u1ed9 3 t\u1eadp \u0111\u1ea7u c\u1ee7a b\u1ed9 s\u01b0u t\u1eadp Ruby l\u00e0m \u0111\u0129 cho trai T\u00e2y. T\u1eadp 4 b\u1eaft \u0111\u1ea7u b\u1eb1ng m\u1ed9t bu\u1ed5i ti\u1ec7c gi\u00e1ng sinh n\u0103m ngo\u00e1i. Ruby v\u00e0 c\u00e1c \u0111\u1ed3ng nghi\u1ec7p t\u1edbi nh\u00e0 m\u1ed9t anh s\u1ebfp c\u00f3 h\u1ed3 b\u01a1i \u0111\u1ec3 l\u00e0m ti\u1ec7c ngo\u00e0i tr\u1eddi. N\u00e0ng trang \u0111i\u1ec3m nh\u1eb9 nh\u00e0ng nh\u01b0ng nh\u00ecn h\u1ebft s\u1ee9c sexy, l\u1ea1i c\u00f2n mang theo m\u1ed9t b\u1ed9 bikini m\u1eb7c nh\u01b0 kh\u00f4ng m\u1eb7c \u0111\u1ec3 thay xu\u1ed1ng h\u1ed3 b\u01a1i. M\u00ecnh h\u1ecfi \u0111\u00f9a \u0111i v\u1edbi \u0111\u1ed3ng nghi\u1ec7p m\u00e0 ch\u1ecdn \u0111\u1ed3 h\u1edf hang th\u1ebf th\u00ec n\u00e0ng b\u1ea3o, v\u0103n ph\u00f2ng em c\u00f3 v\u00e0i anh nh\u00e2n vi\u00ean m\u1edbi \u0111\u1eb9p trai l\u1eafm, bi\u1ebft \u0111\u00e2u \u0111\u01b0\u1ee3c. T\u1ed1i h\u00f4m \u0111\u00f3 m\u00ecnh \u0111\u1ebfn \u0111\u00f3n th\u00ec Ruby \u0111\u00e3 s\u01b0\u01a1ng s\u01b0\u01a1ng v\u00e0i ly r\u01b0\u1ee3u vang, m\u1eb7t \u1eedng \u0111\u1ecf nh\u00ecn h\u1ebft s\u1ee9c quy\u1ebfn r\u0169. N\u00e0ng chui v\u00e0o xe h\u00f4n m\u00ecnh l\u00e0 m\u00ecnh nghe ra ngay c\u00f3 m\u00f9i n\u01b0\u1edbc hoa \u0111\u00e0n \u00f4ng. M\u00ecnh nh\u00e1y m\u1eaft h\u1ecfi ti\u1ec7c th\u1ebf n\u00e0o th\u00ec n\u00e0ng ch\u1ec9 c\u01b0\u1eddi m\u1ec9m chi r\u1ed3i b\u1ea3o m\u00ecnh l\u00e1i v\u1ec1 nh\u00e0 \u0111i. V\u00e0o t\u1edbi nh\u00e0 th\u00ec n\u00e0ng quay qua \u00f4m m\u00ecnh v\u00e0 th\u1ea7m th\u00ec- Ruby: anh \u01a1i h\u00f4m nay em h\u01b0 m\u1ea5t r\u1ed3i.- m\u00ecnh: hihi, anh bi\u1ebft ngay m\u00e0. Em \u0111\u1ea7y m\u00f9i n\u01b0\u1edbc hoa \u0111\u00e0n \u00f4ng. Th\u1ebf em \u0111\u1ee5 anh \u0111\u1ed3ng nghi\u1ec7p n\u00e0o r\u1ed3i?- Ruby: trong l\u00fac thay \u0111\u1ed3 b\u01a1i ra \u0111\u1ec3 chu\u1ea9n b\u1ecb ra anh \u0111\u00f3n th\u00ec em nghe g\u00f5 c\u1eeda, m\u1edf ra th\u00ec th\u1ea5y anh Andy da \u0111en \u0111\u1ee9ng \u1edf ngo\u00e0i. L\u00fac \u1edf ngo\u00e0i h\u1ed3 b\u01a1i em c\u00f3 nh\u00ecn anh Andy n\u00e0y k\u1ef9 l\u1eafm, v\u00ec c\u01a1 th\u1ec3 r\u1ea5t c\u01a1 b\u1eafp. Anh \u1ea5y b\u1ea3o c\u00f3 th\u1ea5y em nh\u00ecn anh \u1ea5y n\u00ean mu\u1ed1n \u0111\u01b0\u1ee3c nh\u00ecn l\u1ea1i em.- m\u00ecnh: r\u1ed3i em n\u00f3i sao?- Ruby: l\u00fac \u0111\u00f3 em \u0111\u00e3 u\u1ed1ng v\u00e0i ly n\u00ean c\u0169ng n\u1ee9ng l\u1eafm anh, n\u00ean em cho anh \u1ea5y v\u00f4 lu\u00f4n...- m\u00ecnh: th\u1ebf r\u1ed3i \u0111\u01b0a l\u1ed3n ra cho \u0111\u1ee5 lu\u00f4n \u00e0?- Ruby: d\u1ea1 em ch\u01b0a d\u00e1m \u0111\u1ee5 v\u00ec ch\u01b0a n\u00f3i cho anh, n\u00ean ch\u1ec9 h\u00f4n h\u00edt anh \u1ea5y r\u1ed3i anh \u1ea5y nh\u1ebft chim v\u00f4 m\u1ed3m cho em th\u1ed5i k\u00e8n th\u00f4i.- m\u00ecnh: th\u00ec ra v\u1ee3 anh v\u1eabn c\u00f2n ngoan th\u1ebf, hehe- Ruby: ng\u01b0\u1eddi ta th\u00e8m con chim \u0111en to \u0111\u00f9ng \u0111\u00f3 l\u1eafm m\u00e0 ph\u1ea3i ki\u1ec1m ch\u1ebf \u0111\u00f3.- m\u00ecnh: anh cho \u0111\u1ee5 lu\u00f4n \u0111\u00f3. R\u1ee7 anh Andy t\u1edbi nh\u00e0 m\u00ecnh \u0111i. Th\u1ebf l\u00e0 v\u00e0i tu\u1ea7n sau, Ruby r\u1ee7 anh Andy n\u00e0y t\u1edbi nh\u00e0, sau khi gi\u1ea3i th\u00edch l\u00e0 m\u00ecnh th\u00edch nh\u00ecn Ruby l\u00e0m \u0111\u0129 cho trai kh\u00e1c. G\u1eb7p anh n\u00e0y r\u1ed3i m\u1edbi th\u1ea5y h\u1ebft h\u1ed3n c\u00e1c b\u00e1c \u1ea1, ng\u01b0\u1eddi g\u00ec m\u00e0 cao nh\u01b0 c\u00e2y c\u1ed9t, c\u01a1 b\u1eafp cu\u1ed3n cu\u1ed9n nh\u01b0 si\u00eau nh\u00e2n, l\u1ea1i c\u00f2n con c\u1eb7c to k\u1ebfch x\u00f9. M\u00ecnh kh\u00f4ng c\u1ea7n k\u1ec3 chi ti\u1ebft c\u1ea3nh \u0111\u1ee5 nhau, c\u00e1c b\u00e1c xem h\u00ecnh s\u1ebd hi\u1ec3u. Ruby \u0111\u01b0\u1ee3c m\u1ed9t bu\u1ed5i \u0111\u1ecbt t\u01a1i t\u1ea3 s\u01b0\u1edbng h\u1ebft l\u1ed3n. N\u00e0ng v\u00e0 anh Andy c\u00f2n h\u1eb9n s\u1ebd g\u1eb7p l\u1ea1i, l\u1ea7n sau s\u1ebd kh\u00f4ng x\u00e0i bao cao su.",
            "content_html": "C\u1ea3m \u01a1n c\u00e1c b\u00e1c \u0111\u1ed3ng d\u00e2m \u0111\u00e3 \u1ee7ng h\u1ed9 3 t\u1eadp \u0111\u1ea7u c\u1ee7a b\u1ed9 s\u01b0u t\u1eadp Ruby l\u00e0m \u0111\u0129 cho trai T\u00e2y.<br><br>T\u1eadp 4 b\u1eaft \u0111\u1ea7u b\u1eb1ng m\u1ed9t bu\u1ed5i ti\u1ec7c gi\u00e1ng sinh n\u0103m ngo\u00e1i. Ruby v\u00e0 c\u00e1c \u0111\u1ed3ng nghi\u1ec7p t\u1edbi nh\u00e0 m\u1ed9t anh s\u1ebfp c\u00f3 h\u1ed3 b\u01a1i \u0111\u1ec3 l\u00e0m ti\u1ec7c ngo\u00e0i tr\u1eddi. N\u00e0ng trang \u0111i\u1ec3m nh\u1eb9 nh\u00e0ng nh\u01b0ng nh\u00ecn h\u1ebft s\u1ee9c sexy, l\u1ea1i c\u00f2n mang theo m\u1ed9t b\u1ed9 bikini m\u1eb7c nh\u01b0 kh\u00f4ng m\u1eb7c \u0111\u1ec3 thay xu\u1ed1ng h\u1ed3 b\u01a1i. M\u00ecnh h\u1ecfi \u0111\u00f9a \u0111i v\u1edbi \u0111\u1ed3ng nghi\u1ec7p m\u00e0 ch\u1ecdn \u0111\u1ed3 h\u1edf hang th\u1ebf th\u00ec n\u00e0ng b\u1ea3o, v\u0103n ph\u00f2ng em c\u00f3 v\u00e0i anh nh\u00e2n vi\u00ean m\u1edbi \u0111\u1eb9p trai l\u1eafm, bi\u1ebft \u0111\u00e2u \u0111\u01b0\u1ee3c.<br><br>T\u1ed1i h\u00f4m \u0111\u00f3 m\u00ecnh \u0111\u1ebfn \u0111\u00f3n th\u00ec Ruby \u0111\u00e3 s\u01b0\u01a1ng s\u01b0\u01a1ng v\u00e0i ly r\u01b0\u1ee3u vang, m\u1eb7t \u1eedng \u0111\u1ecf nh\u00ecn h\u1ebft s\u1ee9c quy\u1ebfn r\u0169. N\u00e0ng chui v\u00e0o xe h\u00f4n m\u00ecnh l\u00e0 m\u00ecnh nghe ra ngay c\u00f3 m\u00f9i n\u01b0\u1edbc hoa \u0111\u00e0n \u00f4ng. M\u00ecnh nh\u00e1y m\u1eaft h\u1ecfi ti\u1ec7c th\u1ebf n\u00e0o th\u00ec n\u00e0ng ch\u1ec9 c\u01b0\u1eddi m\u1ec9m chi r\u1ed3i b\u1ea3o m\u00ecnh l\u00e1i v\u1ec1 nh\u00e0 \u0111i.<br><br>V\u00e0o t\u1edbi nh\u00e0 th\u00ec n\u00e0ng quay qua \u00f4m m\u00ecnh v\u00e0 th\u1ea7m th\u00ec<br>- Ruby: anh \u01a1i h\u00f4m nay em h\u01b0 m\u1ea5t r\u1ed3i.<br>- m\u00ecnh: hihi, anh bi\u1ebft ngay m\u00e0. Em \u0111\u1ea7y m\u00f9i n\u01b0\u1edbc hoa \u0111\u00e0n \u00f4ng. Th\u1ebf em \u0111\u1ee5 anh \u0111\u1ed3ng nghi\u1ec7p n\u00e0o r\u1ed3i?<br>- Ruby: trong l\u00fac thay \u0111\u1ed3 b\u01a1i ra \u0111\u1ec3 chu\u1ea9n b\u1ecb ra anh \u0111\u00f3n th\u00ec em nghe g\u00f5 c\u1eeda, m\u1edf ra th\u00ec th\u1ea5y anh Andy da \u0111en \u0111\u1ee9ng \u1edf ngo\u00e0i. L\u00fac \u1edf ngo\u00e0i h\u1ed3 b\u01a1i em c\u00f3 nh\u00ecn anh Andy n\u00e0y k\u1ef9 l\u1eafm, v\u00ec c\u01a1 th\u1ec3 r\u1ea5t c\u01a1 b\u1eafp. Anh \u1ea5y b\u1ea3o c\u00f3 th\u1ea5y em nh\u00ecn anh \u1ea5y n\u00ean mu\u1ed1n \u0111\u01b0\u1ee3c nh\u00ecn l\u1ea1i em.<br>- m\u00ecnh: r\u1ed3i em n\u00f3i sao?<br>- Ruby: l\u00fac \u0111\u00f3 em \u0111\u00e3 u\u1ed1ng v\u00e0i ly n\u00ean c\u0169ng n\u1ee9ng l\u1eafm anh, n\u00ean em cho anh \u1ea5y v\u00f4 lu\u00f4n...<br>- m\u00ecnh: th\u1ebf r\u1ed3i \u0111\u01b0a l\u1ed3n ra cho \u0111\u1ee5 lu\u00f4n \u00e0?<br>- Ruby: d\u1ea1 em ch\u01b0a d\u00e1m \u0111\u1ee5 v\u00ec ch\u01b0a n\u00f3i cho anh, n\u00ean ch\u1ec9 h\u00f4n h\u00edt anh \u1ea5y r\u1ed3i anh \u1ea5y nh\u1ebft chim v\u00f4 m\u1ed3m cho em th\u1ed5i k\u00e8n th\u00f4i.<br>- m\u00ecnh: th\u00ec ra v\u1ee3 anh v\u1eabn c\u00f2n ngoan th\u1ebf, hehe<br>- Ruby: ng\u01b0\u1eddi ta th\u00e8m con chim \u0111en to \u0111\u00f9ng \u0111\u00f3 l\u1eafm m\u00e0 ph\u1ea3i ki\u1ec1m ch\u1ebf \u0111\u00f3.<br>- m\u00ecnh: anh cho \u0111\u1ee5 lu\u00f4n \u0111\u00f3. R\u1ee7 anh Andy t\u1edbi nh\u00e0 m\u00ecnh \u0111i.<br><br>Th\u1ebf l\u00e0 v\u00e0i tu\u1ea7n sau, Ruby r\u1ee7 anh Andy n\u00e0y t\u1edbi nh\u00e0, sau khi gi\u1ea3i th\u00edch l\u00e0 m\u00ecnh th\u00edch nh\u00ecn Ruby l\u00e0m \u0111\u0129 cho trai kh\u00e1c. G\u1eb7p anh n\u00e0y r\u1ed3i m\u1edbi th\u1ea5y h\u1ebft h\u1ed3n c\u00e1c b\u00e1c \u1ea1, ng\u01b0\u1eddi g\u00ec m\u00e0 cao nh\u01b0 c\u00e2y c\u1ed9t, c\u01a1 b\u1eafp cu\u1ed3n cu\u1ed9n nh\u01b0 si\u00eau nh\u00e2n, l\u1ea1i c\u00f2n con c\u1eb7c to k\u1ebfch x\u00f9. M\u00ecnh kh\u00f4ng c\u1ea7n k\u1ec3 chi ti\u1ebft c\u1ea3nh \u0111\u1ee5 nhau, c\u00e1c b\u00e1c xem h\u00ecnh s\u1ebd hi\u1ec3u. Ruby \u0111\u01b0\u1ee3c m\u1ed9t bu\u1ed5i \u0111\u1ecbt t\u01a1i t\u1ea3 s\u01b0\u1edbng h\u1ebft l\u1ed3n. N\u00e0ng v\u00e0 anh Andy c\u00f2n h\u1eb9n s\u1ebd g\u1eb7p l\u1ea1i, l\u1ea7n sau s\u1ebd kh\u00f4ng x\u00e0i bao cao su.<br><br><br> <script class=\"js-extraPhrases\" type=\"application\/json\"> { \"lightbox_close\": \"Close\", \"lightbox_next\": \"Next\", \"lightbox_previous\": \"Previous\", \"lightbox_error\": \"The requested content cannot be loaded. Please try again later.\", \"lightbox_start_slideshow\": \"Start slideshow\", \"lightbox_stop_slideshow\": \"Stop slideshow\", \"lightbox_full_screen\": \"Full screen\", \"lightbox_thumbnails\": \"Thumbnails\", \"lightbox_download\": \"Download\", \"lightbox_share\": \"Share\", \"lightbox_zoom\": \"Zoom\", \"lightbox_new_window\": \"New window\", \"lightbox_toggle_sidebar\": \"Toggle sidebar\" } <\/script> <div class=\"bbImageWrapper js-lbImage\" title=\"IMG_20210115_153321.jpg\" data-src=\"https:\/\/greenupload.com\/images\/2021\/01\/15\/IMG_20210115_153321.jpg\" data-lb-sidebar-href=\"\" data-lb-caption-extra-html=\"\" data-single-image=\"1\"> <img src=\"https:\/\/greenupload.com\/images\/2021\/01\/15\/IMG_20210115_153321.jpg\" data-url=\"https:\/\/greenupload.com\/images\/2021\/01\/15\/IMG_20210115_153321.jpg\" class=\"bbImage\" data-zoom-target=\"1\" style=\"\" alt=\"IMG_20210115_153321.jpg\" title=\"\" width=\"\" height=\"\" loading=\"lazy\"> <\/div> <br> <div class=\"bbImageWrapper js-lbImage\" title=\"IMG_20210115_153249.jpg\" data-src=\"https:\/\/greenupload.com\/images\/2021\/01\/15\/IMG_20210115_153249.jpg\" data-lb-sidebar-href=\"\" data-lb-caption-extra-html=\"\" data-single-image=\"1\"> <img src=\"https:\/\/greenupload.com\/images\/2021\/01\/15\/IMG_20210115_153249.jpg\" data-url=\"https:\/\/greenupload.com\/images\/2021\/01\/15\/IMG_20210115_153249.jpg\" class=\"bbImage\" data-zoom-target=\"1\" style=\"\" alt=\"IMG_20210115_153249.jpg\" title=\"\" width=\"\" height=\"\" loading=\"lazy\"> <\/div> <br> <div class=\"bbImageWrapper js-lbImage\" title=\"IMG_20210115_153213.jpg\" data-src=\"https:\/\/greenupload.com\/images\/2021\/01\/15\/IMG_20210115_153213.jpg\" data-lb-sidebar-href=\"\" data-lb-caption-extra-html=\"\" data-single-image=\"1\"> <img src=\"https:\/\/greenupload.com\/images\/2021\/01\/15\/IMG_20210115_153213.jpg\" data-url=\"https:\/\/greenupload.com\/images\/2021\/01\/15\/IMG_20210115_153213.jpg\" class=\"bbImage\" data-zoom-target=\"1\" style=\"\" alt=\"IMG_20210115_153213.jpg\" title=\"\" width=\"\" height=\"\" loading=\"lazy\"> <\/div> <br> <div class=\"bbImageWrapper js-lbImage\" title=\"IMG_20210115_152951.jpg\" data-src=\"https:\/\/greenupload.com\/images\/2021\/01\/15\/IMG_20210115_152951.jpg\" data-lb-sidebar-href=\"\" data-lb-caption-extra-html=\"\" data-single-image=\"1\"> <img src=\"https:\/\/greenupload.com\/images\/2021\/01\/15\/IMG_20210115_152951.jpg\" data-url=\"https:\/\/greenupload.com\/images\/2021\/01\/15\/IMG_20210115_152951.jpg\" class=\"bbImage\" data-zoom-target=\"1\" style=\"\" alt=\"IMG_20210115_152951.jpg\" title=\"\" width=\"\" height=\"\" loading=\"lazy\"> <\/div> <br> <div class=\"bbImageWrapper js-lbImage\" title=\"IMG_20210115_152927.jpg\" data-src=\"https:\/\/greenupload.com\/images\/2021\/01\/15\/IMG_20210115_152927.jpg\" data-lb-sidebar-href=\"\" data-lb-caption-extra-html=\"\" data-single-image=\"1\"> <img src=\"https:\/\/greenupload.com\/images\/2021\/01\/15\/IMG_20210115_152927.jpg\" data-url=\"https:\/\/greenupload.com\/images\/2021\/01\/15\/IMG_20210115_152927.jpg\" class=\"bbImage\" data-zoom-target=\"1\" style=\"\" alt=\"IMG_20210115_152927.jpg\" title=\"\" width=\"\" height=\"\" loading=\"lazy\"> <\/div> <br> <div class=\"bbImageWrapper js-lbImage\" title=\"IMG_20210115_153032.jpg\" data-src=\"https:\/\/greenupload.com\/images\/2021\/01\/15\/IMG_20210115_153032.jpg\" data-lb-sidebar-href=\"\" data-lb-caption-extra-html=\"\" data-single-image=\"1\"> <img src=\"https:\/\/greenupload.com\/images\/2021\/01\/15\/IMG_20210115_153032.jpg\" data-url=\"https:\/\/greenupload.com\/images\/2021\/01\/15\/IMG_20210115_153032.jpg\" class=\"bbImage\" data-zoom-target=\"1\" style=\"\" alt=\"IMG_20210115_153032.jpg\" title=\"\" width=\"\" height=\"\" loading=\"lazy\"> <\/div> <br> <div class=\"bbImageWrapper js-lbImage\" title=\"Screenshot_20210115_153611.jpg\" data-src=\"https:\/\/greenupload.com\/images\/2021\/01\/15\/Screenshot_20210115_153611.jpg\" data-lb-sidebar-href=\"\" data-lb-caption-extra-html=\"\" data-single-image=\"1\"> <img src=\"https:\/\/greenupload.com\/images\/2021\/01\/15\/Screenshot_20210115_153611.jpg\" data-url=\"https:\/\/greenupload.com\/images\/2021\/01\/15\/Screenshot_20210115_153611.jpg\" class=\"bbImage\" data-zoom-target=\"1\" style=\"\" alt=\"Screenshot_20210115_153611.jpg\" title=\"\" width=\"\" height=\"\" loading=\"lazy\"> <\/div> <br> <div class=\"bbImageWrapper js-lbImage\" title=\"Screenshot_20210115_153724.jpg\" data-src=\"https:\/\/greenupload.com\/images\/2021\/01\/15\/Screenshot_20210115_153724.jpg\" data-lb-sidebar-href=\"\" data-lb-caption-extra-html=\"\" data-single-image=\"1\"> <img src=\"https:\/\/greenupload.com\/images\/2021\/01\/15\/Screenshot_20210115_153724.jpg\" data-url=\"https:\/\/greenupload.com\/images\/2021\/01\/15\/Screenshot_20210115_153724.jpg\" class=\"bbImage\" data-zoom-target=\"1\" style=\"\" alt=\"Screenshot_20210115_153724.jpg\" title=\"\" width=\"\" height=\"\" loading=\"lazy\"> <\/div> <br> <div class=\"bbImageWrapper js-lbImage\" title=\"Screenshot_20210115_153706.jpg\" data-src=\"https:\/\/greenupload.com\/images\/2021\/01\/15\/Screenshot_20210115_153706.jpg\" data-lb-sidebar-href=\"\" data-lb-caption-extra-html=\"\" data-single-image=\"1\"> <img src=\"https:\/\/greenupload.com\/images\/2021\/01\/15\/Screenshot_20210115_153706.jpg\" data-url=\"https:\/\/greenupload.com\/images\/2021\/01\/15\/Screenshot_20210115_153706.jpg\" class=\"bbImage\" data-zoom-target=\"1\" style=\"\" alt=\"Screenshot_20210115_153706.jpg\" title=\"\" width=\"\" height=\"\" loading=\"lazy\"> <\/div>",
            "link_uuid": "f889ced7-fd8a-42f3-ab9b-c819970a84d6",
            "post_id": "post-34967305",
            "status": "PROCESSED_NO_IMG",
            "download_links_status": "PROCESSED_NO_LINKS",
            "type": "MAIN_POST",
            "total_image": "0",
            "created_at": "2021-06-19 16:23:40"
        },
        {
            "uuid": "bea45fce-49ce-48bd-8daa-263d3a243757",
            "author": "htman.dung",
            "content": "Cha\u0300o ca\u0301c \u0111\u00f4\u0300ng d\u00e2m, \u0110a\u0303 l\u00e2u l\u0103\u0301m r\u00f4\u0300i em m\u1edbi cho Ruby nh\u00e0 em l\u00ean s\u00f3ng l\u1ea1i. Ruby v\u1eabn \u0111\u1ec1u \u0111\u1eb7n giao ph\u1ed1i v\u1edbi trai T\u00e2y \u00edt nh\u1ea5t 1 th\u00e1ng 1 l\u1ea7n, nh\u01b0ng em v\u1ed1n l\u01b0\u1eddi n\u00ean kh\u00f4ng \u0111\u0103ng b\u00e0i th\u01b0\u1eddng xuy\u00ean, haha. 2 th\u00e1ng tr\u01b0\u1edbc Ruby nh\u00e0 em c\u00f3 l\u00e0m quen \u0111\u01b0\u1ee3c v\u1edbi 1 anh T\u00e2y tr\u1eafng c\u00f3 h\u00e0ng thu\u1ed9c lo\u1ea1i kh\u1ee7ng, ngay c\u1ea3 so v\u1edbi ti\u00eau chu\u1ea9n b\u00ean n\u00e0y (c\u00e1c b\u00e1c xem h\u00ecnh d\u01b0\u1edbi \u0111\u00e2y s\u1ebd th\u1ea5y). Anh n\u00e0y l\u1ea1i c\u00f2n c\u00f3 c\u01a1 b\u1eafp v\u00e0 \u0111\u1eb9p trai n\u00ean Ruby m\u00ea l\u1eafm. M\u1ed7i l\u1ea7n l\u00e0m t\u00ecnh \u0111\u1ec1u r\u00ean r\u1ec9 (b\u1eb1ng ti\u1ebfng Anh) \"em th\u00edch c\u1eb7c anh l\u1eafm. Anh \u0111\u00e2m v\u00f4 l\u1ed3n em s\u01b0\u1edbng l\u1eafm. B\u1eafn tinh v\u00f4 trong em lu\u00f4n \u0111i anh\", l\u00e0m em \u0111\u1ee9ng xem m\u00e0 c\u1ee9ng h\u1ebft c\u1ea3 l\u00ean. C\u00e1ch \u0111\u00e2y v\u00e0i tu\u1ea7n, em h\u1ecfi th\u1eed Ruby c\u00f3 mu\u1ed1n \u0111\u01b0\u1ee3c 1 anh t\u00e2y tr\u1eafng v\u00e0 1 anh t\u00e2y \u0111en ph\u1ee5c v\u1ee5 1 l\u00fac kh\u00f4ng th\u00ec n\u00e0ng g\u1eadt \u0111\u1ea7u ngay (d\u00e2m kh\u00f4ng ch\u1ecbu \u0111\u01b0\u1ee3c). Th\u1ebf l\u00e0 em li\u00ean h\u1ec7 anh t\u00e2y tr\u1eafng n\u00e0y, v\u00e0 r\u1ee7 th\u00eam anh t\u00e2y \u0111en \u0111\u00e3 xu\u1ea5t hi\u1ec7n trong t\u1eadp 2. Ruby h\u00e0o h\u1ee9ng l\u1eafm. T\u1ed1i tr\u01b0\u1edbc \u0111\u00f3 c\u00f2n th\u01b0\u1edfng cho em 1 m\u00e0n m\u00faa tho\u00e1t y v\u00e0 th\u1ed5i k\u00e8n nu\u1ed1t tinh \u0111\u1ec3 c\u1ea3m \u01a1n em \u0111\u00e3 cho n\u00e0ng th\u1ecfa d\u1ee5c v\u1ecdng. T\u1edbi ng\u00e0y h\u1eb9n l\u00e0 \u0111\u00fang k\u1ef3 r\u1ee5ng tr\u1ee9ng n\u00ean \u0111\u1ed9 d\u00e2m c\u1ee7a Ruby l\u00ean t\u1edbi \u0111\u1ec9nh. C\u00e1c b\u00e1c xem h\u00ecnh d\u01b0\u1edbi \u0111\u00e2y s\u1ebd th\u1ea5y 2 anh t\u00e2y h\u00e0ng to \u0111\u00f9ng thay phi\u00ean ph\u1ee5c v\u1ee5 m\u00e0 c\u0169ng m\u1ea5t g\u1ea7n 3 ti\u1ebfng, m\u1ed7i anh b\u1eafn 2 ph\u00e1t, m\u1edbi th\u1ecfa m\u00e3n \u0111\u0129 d\u00e2m nh\u00e0 em. C\u00e1i hay l\u00e0 l\u1ed3n Ruby m\u1eb7c d\u00f9 \u0111\u00e3 r\u1ea5t nhi\u1ec1u chu\u1ed1i to \u0111\u00e2m v\u00e0o nh\u01b0ng v\u1eabn r\u1ea5t kh\u00edt l\u00e0m cho trai n\u00e0o c\u0169ng th\u00edch m\u00ea.",
            "content_html": "Cha\u0300o ca\u0301c \u0111\u00f4\u0300ng d\u00e2m,<br><br>\u0110a\u0303 l\u00e2u l\u0103\u0301m r\u00f4\u0300i em m\u1edbi cho Ruby nh\u00e0 em l\u00ean s\u00f3ng l\u1ea1i. Ruby v\u1eabn \u0111\u1ec1u \u0111\u1eb7n giao ph\u1ed1i v\u1edbi trai T\u00e2y \u00edt nh\u1ea5t 1 th\u00e1ng 1 l\u1ea7n, nh\u01b0ng em v\u1ed1n l\u01b0\u1eddi n\u00ean kh\u00f4ng \u0111\u0103ng b\u00e0i th\u01b0\u1eddng xuy\u00ean, haha.<br><br>2 th\u00e1ng tr\u01b0\u1edbc Ruby nh\u00e0 em c\u00f3 l\u00e0m quen \u0111\u01b0\u1ee3c v\u1edbi 1 anh T\u00e2y tr\u1eafng c\u00f3 h\u00e0ng thu\u1ed9c lo\u1ea1i kh\u1ee7ng, ngay c\u1ea3 so v\u1edbi ti\u00eau chu\u1ea9n b\u00ean n\u00e0y (c\u00e1c b\u00e1c xem h\u00ecnh d\u01b0\u1edbi \u0111\u00e2y s\u1ebd th\u1ea5y). Anh n\u00e0y l\u1ea1i c\u00f2n c\u00f3 c\u01a1 b\u1eafp v\u00e0 \u0111\u1eb9p trai n\u00ean Ruby m\u00ea l\u1eafm. M\u1ed7i l\u1ea7n l\u00e0m t\u00ecnh \u0111\u1ec1u r\u00ean r\u1ec9 (b\u1eb1ng ti\u1ebfng Anh) \"em th\u00edch c\u1eb7c anh l\u1eafm. Anh \u0111\u00e2m v\u00f4 l\u1ed3n em s\u01b0\u1edbng l\u1eafm. B\u1eafn tinh v\u00f4 trong em lu\u00f4n \u0111i anh\", l\u00e0m em \u0111\u1ee9ng xem m\u00e0 c\u1ee9ng h\u1ebft c\u1ea3 l\u00ean.<br><br>C\u00e1ch \u0111\u00e2y v\u00e0i tu\u1ea7n, em h\u1ecfi th\u1eed Ruby c\u00f3 mu\u1ed1n \u0111\u01b0\u1ee3c 1 anh t\u00e2y tr\u1eafng v\u00e0 1 anh t\u00e2y \u0111en ph\u1ee5c v\u1ee5 1 l\u00fac kh\u00f4ng th\u00ec n\u00e0ng g\u1eadt \u0111\u1ea7u ngay (d\u00e2m kh\u00f4ng ch\u1ecbu \u0111\u01b0\u1ee3c). Th\u1ebf l\u00e0 em li\u00ean h\u1ec7 anh t\u00e2y tr\u1eafng n\u00e0y, v\u00e0 r\u1ee7 th\u00eam anh t\u00e2y \u0111en \u0111\u00e3 xu\u1ea5t hi\u1ec7n trong t\u1eadp 2. Ruby h\u00e0o h\u1ee9ng l\u1eafm. T\u1ed1i tr\u01b0\u1edbc \u0111\u00f3 c\u00f2n th\u01b0\u1edfng cho em 1 m\u00e0n m\u00faa tho\u00e1t y v\u00e0 th\u1ed5i k\u00e8n nu\u1ed1t tinh \u0111\u1ec3 c\u1ea3m \u01a1n em \u0111\u00e3 cho n\u00e0ng th\u1ecfa d\u1ee5c v\u1ecdng.<br><br>T\u1edbi ng\u00e0y h\u1eb9n l\u00e0 \u0111\u00fang k\u1ef3 r\u1ee5ng tr\u1ee9ng n\u00ean \u0111\u1ed9 d\u00e2m c\u1ee7a Ruby l\u00ean t\u1edbi \u0111\u1ec9nh. C\u00e1c b\u00e1c xem h\u00ecnh d\u01b0\u1edbi \u0111\u00e2y s\u1ebd th\u1ea5y 2 anh t\u00e2y h\u00e0ng to \u0111\u00f9ng thay phi\u00ean ph\u1ee5c v\u1ee5 m\u00e0 c\u0169ng m\u1ea5t g\u1ea7n 3 ti\u1ebfng, m\u1ed7i anh b\u1eafn 2 ph\u00e1t, m\u1edbi th\u1ecfa m\u00e3n \u0111\u0129 d\u00e2m nh\u00e0 em. C\u00e1i hay l\u00e0 l\u1ed3n Ruby m\u1eb7c d\u00f9 \u0111\u00e3 r\u1ea5t nhi\u1ec1u chu\u1ed1i to \u0111\u00e2m v\u00e0o nh\u01b0ng v\u1eabn r\u1ea5t kh\u00edt l\u00e0m cho trai n\u00e0o c\u0169ng th\u00edch m\u00ea.<br><br> <script class=\"js-extraPhrases\" type=\"application\/json\"> { \"lightbox_close\": \"Close\", \"lightbox_next\": \"Next\", \"lightbox_previous\": \"Previous\", \"lightbox_error\": \"The requested content cannot be loaded. Please try again later.\", \"lightbox_start_slideshow\": \"Start slideshow\", \"lightbox_stop_slideshow\": \"Stop slideshow\", \"lightbox_full_screen\": \"Full screen\", \"lightbox_thumbnails\": \"Thumbnails\", \"lightbox_download\": \"Download\", \"lightbox_share\": \"Share\", \"lightbox_zoom\": \"Zoom\", \"lightbox_new_window\": \"New window\", \"lightbox_toggle_sidebar\": \"Toggle sidebar\" } <\/script> <div class=\"bbImageWrapper js-lbImage\" title=\"IMG_4598-3.jpg\" data-src=\"https:\/\/greenupload.com\/images\/2018\/11\/18\/IMG_4598-3.jpg\" data-lb-sidebar-href=\"\" data-lb-caption-extra-html=\"\" data-single-image=\"1\"> <img src=\"https:\/\/greenupload.com\/images\/2018\/11\/18\/IMG_4598-3.jpg\" data-url=\"https:\/\/greenupload.com\/images\/2018\/11\/18\/IMG_4598-3.jpg\" class=\"bbImage\" data-zoom-target=\"1\" style=\"\" alt=\"IMG_4598-3.jpg\" title=\"\" width=\"\" height=\"\" loading=\"lazy\"> <\/div> <br><br> <div class=\"bbImageWrapper js-lbImage\" title=\"IMG_4597-2.jpg\" data-src=\"https:\/\/greenupload.com\/images\/2018\/11\/18\/IMG_4597-2.jpg\" data-lb-sidebar-href=\"\" data-lb-caption-extra-html=\"\" data-single-image=\"1\"> <img src=\"https:\/\/greenupload.com\/images\/2018\/11\/18\/IMG_4597-2.jpg\" data-url=\"https:\/\/greenupload.com\/images\/2018\/11\/18\/IMG_4597-2.jpg\" class=\"bbImage\" data-zoom-target=\"1\" style=\"\" alt=\"IMG_4597-2.jpg\" title=\"\" width=\"\" height=\"\" loading=\"lazy\"> <\/div> <br><br> <div class=\"bbImageWrapper js-lbImage\" title=\"IMG_4592-1.jpg\" data-src=\"https:\/\/greenupload.com\/images\/2018\/11\/18\/IMG_4592-1.jpg\" data-lb-sidebar-href=\"\" data-lb-caption-extra-html=\"\" data-single-image=\"1\"> <img src=\"https:\/\/greenupload.com\/images\/2018\/11\/18\/IMG_4592-1.jpg\" data-url=\"https:\/\/greenupload.com\/images\/2018\/11\/18\/IMG_4592-1.jpg\" class=\"bbImage\" data-zoom-target=\"1\" style=\"\" alt=\"IMG_4592-1.jpg\" title=\"\" width=\"\" height=\"\" loading=\"lazy\"> <\/div> <br><br> <div class=\"bbImageWrapper js-lbImage\" title=\"IMG_4599-4.jpg\" data-src=\"https:\/\/greenupload.com\/images\/2018\/11\/18\/IMG_4599-4.jpg\" data-lb-sidebar-href=\"\" data-lb-caption-extra-html=\"\" data-single-image=\"1\"> <img src=\"https:\/\/greenupload.com\/images\/2018\/11\/18\/IMG_4599-4.jpg\" data-url=\"https:\/\/greenupload.com\/images\/2018\/11\/18\/IMG_4599-4.jpg\" class=\"bbImage\" data-zoom-target=\"1\" style=\"\" alt=\"IMG_4599-4.jpg\" title=\"\" width=\"\" height=\"\" loading=\"lazy\"> <\/div> <br><br> <div class=\"bbImageWrapper js-lbImage\" title=\"IMG_4601-5.jpg\" data-src=\"https:\/\/greenupload.com\/images\/2018\/11\/18\/IMG_4601-5.jpg\" data-lb-sidebar-href=\"\" data-lb-caption-extra-html=\"\" data-single-image=\"1\"> <img src=\"https:\/\/greenupload.com\/images\/2018\/11\/18\/IMG_4601-5.jpg\" data-url=\"https:\/\/greenupload.com\/images\/2018\/11\/18\/IMG_4601-5.jpg\" class=\"bbImage\" data-zoom-target=\"1\" style=\"\" alt=\"IMG_4601-5.jpg\" title=\"\" width=\"\" height=\"\" loading=\"lazy\"> <\/div> <br><br> <div class=\"bbImageWrapper js-lbImage\" title=\"IMG_4602-6.jpg\" data-src=\"https:\/\/greenupload.com\/images\/2018\/11\/18\/IMG_4602-6.jpg\" data-lb-sidebar-href=\"\" data-lb-caption-extra-html=\"\" data-single-image=\"1\"> <img src=\"https:\/\/greenupload.com\/images\/2018\/11\/18\/IMG_4602-6.jpg\" data-url=\"https:\/\/greenupload.com\/images\/2018\/11\/18\/IMG_4602-6.jpg\" class=\"bbImage\" data-zoom-target=\"1\" style=\"\" alt=\"IMG_4602-6.jpg\" title=\"\" width=\"\" height=\"\" loading=\"lazy\"> <\/div> <br> <div class=\"bbImageWrapper js-lbImage\" title=\"0NdiX\" data-src=\"https:\/\/greenupload.com\/image\/0NdiX\" data-lb-sidebar-href=\"\" data-lb-caption-extra-html=\"\" data-single-image=\"1\"> <img src=\"https:\/\/greenupload.com\/image\/0NdiX\" data-url=\"https:\/\/greenupload.com\/image\/0NdiX\" class=\"bbImage\" data-zoom-target=\"1\" style=\"\" alt=\"0NdiX\" title=\"\" width=\"\" height=\"\" loading=\"lazy\"> <\/div>",
            "link_uuid": "203e1335-d421-49ab-a391-da0c41a6a705",
            "post_id": "post-34545976",
            "status": "PROCESSED_NO_IMG",
            "download_links_status": "PROCESSED_NO_LINKS",
            "type": "MAIN_POST",
            "total_image": "0",
            "created_at": "2021-06-19 16:23:40"
        },
        {
            "uuid": "d1720299-2853-4564-ac85-11e274eb9b53",
            "author": "htman.dung",
            "content": "Em g\u1eedi lu\u00f4n c\u00e1c b\u00e1c h\u00ecnh chu\u1ed1i T\u00e2y c\u1ee7a anh n\u00e0y. Ruby c\u1ee9 ng\u1eafm t\u1ea5m h\u00ecnh n\u00e0y tr\u00ean \u0111i\u1ec7n tho\u1ea1i l\u00e0 l\u1ed3n \u0111\u00e3 \u01b0\u1edbt h\u1ebft c\u1ea3.",
            "content_html": "Em g\u1eedi lu\u00f4n c\u00e1c b\u00e1c h\u00ecnh chu\u1ed1i T\u00e2y c\u1ee7a anh n\u00e0y. Ruby c\u1ee9 ng\u1eafm t\u1ea5m h\u00ecnh n\u00e0y tr\u00ean \u0111i\u1ec7n tho\u1ea1i l\u00e0 l\u1ed3n \u0111\u00e3 \u01b0\u1edbt h\u1ebft c\u1ea3.<br><br> <div class=\"bbImageWrapper js-lbImage\" title=\"7d22fd32-db9d-4e9a-8bb5-bb33385eba25.jpg\" data-src=\"https:\/\/greenupload.com\/images\/2018\/11\/18\/7d22fd32-db9d-4e9a-8bb5-bb33385eba25.jpg\" data-lb-sidebar-href=\"\" data-lb-caption-extra-html=\"\" data-single-image=\"1\"> <img src=\"https:\/\/greenupload.com\/images\/2018\/11\/18\/7d22fd32-db9d-4e9a-8bb5-bb33385eba25.jpg\" data-url=\"https:\/\/greenupload.com\/images\/2018\/11\/18\/7d22fd32-db9d-4e9a-8bb5-bb33385eba25.jpg\" class=\"bbImage\" data-zoom-target=\"1\" style=\"\" alt=\"7d22fd32-db9d-4e9a-8bb5-bb33385eba25.jpg\" title=\"\" width=\"\" height=\"\" loading=\"lazy\"> <\/div>",
            "link_uuid": "d4b5919f-336d-4b2d-af98-9efc5dbf51a9",
            "post_id": "post-30473607",
            "status": "PROCESSED_NO_IMG",
            "download_links_status": "PROCESSED_NO_LINKS",
            "type": "MAIN_POST",
            "total_image": "0",
            "created_at": "2021-06-19 16:23:40"
        },
        {
            "uuid": "d21f5952-a6b7-4626-8815-287b693c7849",
            "author": "htman.dung",
            "content": "Ch\u00e0o c\u00e1c b\u00e1c, S\u1ed1 l\u00e0 em v\u00e0 G\u1ea5u theo d\u00f5i thiendia c\u0169ng l\u00e2u l\u1eafm r\u1ed3i nh\u01b0ng ch\u01b0a bao gi\u1edd post b\u00e0i report g\u00ec c\u1ea3. 2 \u0111\u1ee9a em \u0111\u1ec1u U25. G\u1ea5u nh\u00e0 em th\u00ec thu\u1ed9c d\u1ea1ng nh\u1ecf ng\u01b0\u1eddi nh\u01b0ng v\u00f2ng n\u00e0o ra v\u00f2ng n\u1ea5y, \u0111\u1eb7c bi\u1ec7t l\u00e0 h\u1ebft s\u1ee9c d\u00e2m \u0111\u00e3ng v\u00e0 k\u1ef9 n\u0103ng l\u00e0m t\u00ecnh th\u1ec9 kh\u1ecfi ch\u00ea. 2 \u0111\u1ee9a em \u0111\u1ec1u kh\u00e1 tho\u00e1ng trong t\u00ecnh d\u1ee5c, some c\u0169ng \u0111\u00e3 nhi\u1ec1u l\u1ea7n nh\u01b0ng h\u1ea7u h\u1ebft \u0111\u1ec1u kh\u00f4ng quay \/ ch\u1ee5p l\u1ea1i v\u00ec l\u00fd do k\u00edn \u0111\u00e1o. Nh\u00e2n d\u1ecbp 2 tu\u1ea7n tr\u01b0\u1edbc, t\u1ee5i em \u0111i tour Ph\u00fa Qu\u1ed1c g\u1eb7p 1 anh T\u00e2y trong \u0111o\u00e0n. G\u1ea5u em v\u1ed1n d\u00e2m s\u1eb5n n\u00ean \u0111\u00e3 \u0111\u1ec3 \u00fd ngay l\u1eadp t\u1ee9c v\u00e0 ra hi\u1ec7u v\u1edbi em l\u00e0 th\u00edch . Th\u1ebf l\u00e0 4 ng\u00e0y \u1edf Ph\u00fa Qu\u1ed1c G\u1ea5u c\u1ee9 di\u1ec7n bikini h\u1ebft s\u1ee9c g\u1ee3i t\u00ecnh, l\u01b0\u1ee3n qua l\u01b0\u1ee3n l\u1ea1i tr\u00f2 chuy\u1ec7n v\u1edbi anh T\u00e2y. Anh n\u00e0y c\u0169ng tinh \u00fd n\u00ean hi\u1ec3u ngay. Th\u1ebf l\u00e0 qua \u0111\u00eam th\u1ee9 2 \u0111\u00e3 m\u00f2 qua ph\u00f2ng 2 \u0111\u1ee9a em \u0111\u1ec3 m\u00e2y m\u01b0a . Em v\u0103n ch\u01b0\u01a1ng d\u1edf n\u00ean kh\u00f4ng bi\u1ebft vi\u1ebft g\u00ec nhi\u1ec1u. Nh\u00e2n d\u1ecbp l\u1ea7n n\u00e0y c\u00f3 ch\u1ee5p l\u1ea1i v\u00e0i t\u1ea5m h\u00ecnh n\u00ean post l\u00ean cho c\u00e1c b\u00e1c coi th\u1eed. B\u00e1c n\u00e0o c\u00f3 h\u1ee9ng th\u00fa th\u00ec c\u1ee9 \u0111\u1ec3 l\u1ea1i coment nh\u00e9. T\u1ee5i em \u1edf Bi\u00ean H\u00f2a",
            "content_html": "Ch\u00e0o c\u00e1c b\u00e1c,<br><br>S\u1ed1 l\u00e0 em v\u00e0 G\u1ea5u theo d\u00f5i thiendia c\u0169ng l\u00e2u l\u1eafm r\u1ed3i nh\u01b0ng ch\u01b0a bao gi\u1edd post b\u00e0i report g\u00ec c\u1ea3. 2 \u0111\u1ee9a em \u0111\u1ec1u U25. G\u1ea5u nh\u00e0 em th\u00ec thu\u1ed9c d\u1ea1ng nh\u1ecf ng\u01b0\u1eddi nh\u01b0ng v\u00f2ng n\u00e0o ra v\u00f2ng n\u1ea5y, \u0111\u1eb7c bi\u1ec7t l\u00e0 h\u1ebft s\u1ee9c d\u00e2m \u0111\u00e3ng v\u00e0 k\u1ef9 n\u0103ng l\u00e0m t\u00ecnh th\u1ec9 kh\u1ecfi ch\u00ea. 2 \u0111\u1ee9a em \u0111\u1ec1u kh\u00e1 tho\u00e1ng trong t\u00ecnh d\u1ee5c, some c\u0169ng \u0111\u00e3 nhi\u1ec1u l\u1ea7n nh\u01b0ng h\u1ea7u h\u1ebft \u0111\u1ec1u kh\u00f4ng quay \/ ch\u1ee5p l\u1ea1i v\u00ec l\u00fd do k\u00edn \u0111\u00e1o.<br><br>Nh\u00e2n d\u1ecbp 2 tu\u1ea7n tr\u01b0\u1edbc, t\u1ee5i em \u0111i tour Ph\u00fa Qu\u1ed1c g\u1eb7p 1 anh T\u00e2y trong \u0111o\u00e0n. G\u1ea5u em v\u1ed1n d\u00e2m s\u1eb5n n\u00ean \u0111\u00e3 \u0111\u1ec3 \u00fd ngay l\u1eadp t\u1ee9c v\u00e0 ra hi\u1ec7u v\u1edbi em l\u00e0 th\u00edch <img src=\"data:image\/gif;base64,R0lGODlhAQABAIAAAAAAAP\/\/\/yH5BAEAAAAALAAAAAABAAEAAAIBRAA7\" class=\"smilie smilie--sprite smilie--sprite1\" alt=\":)\" title=\"Smile :)\" loading=\"lazy\" data-shortname=\":)\">. Th\u1ebf l\u00e0 4 ng\u00e0y \u1edf Ph\u00fa Qu\u1ed1c G\u1ea5u c\u1ee9 di\u1ec7n bikini h\u1ebft s\u1ee9c g\u1ee3i t\u00ecnh, l\u01b0\u1ee3n qua l\u01b0\u1ee3n l\u1ea1i tr\u00f2 chuy\u1ec7n v\u1edbi anh T\u00e2y. Anh n\u00e0y c\u0169ng tinh \u00fd n\u00ean hi\u1ec3u ngay. Th\u1ebf l\u00e0 qua \u0111\u00eam th\u1ee9 2 \u0111\u00e3 m\u00f2 qua ph\u00f2ng 2 \u0111\u1ee9a em \u0111\u1ec3 m\u00e2y m\u01b0a <img src=\"data:image\/gif;base64,R0lGODlhAQABAIAAAAAAAP\/\/\/yH5BAEAAAAALAAAAAABAAEAAAIBRAA7\" class=\"smilie smilie--sprite smilie--sprite1\" alt=\":)\" title=\"Smile :)\" loading=\"lazy\" data-shortname=\":)\">. Em v\u0103n ch\u01b0\u01a1ng d\u1edf n\u00ean kh\u00f4ng bi\u1ebft vi\u1ebft g\u00ec nhi\u1ec1u. Nh\u00e2n d\u1ecbp l\u1ea7n n\u00e0y c\u00f3 ch\u1ee5p l\u1ea1i v\u00e0i t\u1ea5m h\u00ecnh n\u00ean post l\u00ean cho c\u00e1c b\u00e1c coi th\u1eed.<br><br>B\u00e1c n\u00e0o c\u00f3 h\u1ee9ng th\u00fa th\u00ec c\u1ee9 \u0111\u1ec3 l\u1ea1i coment nh\u00e9. T\u1ee5i em \u1edf Bi\u00ean H\u00f2a<br><br><a href=\"https:\/\/greenupload.com\/server7\/image\/J2kAV8\" target=\"_blank\" class=\"link link--external\" rel=\"nofollow ugc noopener\"> <img src=\"https:\/\/greenupload.com\/server7\/images\/2016\/08\/11\/20160811-96d441.jpg\" data-url=\"https:\/\/greenupload.com\/server7\/images\/2016\/08\/11\/20160811-96d441.jpg\" class=\"bbImage \" loading=\"lazy\" style=\"\" width=\"\" height=\"\"> <\/a><br><a href=\"https:\/\/greenupload.com\/server7\/image\/J2kUPR\" target=\"_blank\" class=\"link link--external\" rel=\"nofollow ugc noopener\"> <img src=\"https:\/\/greenupload.com\/server7\/images\/2016\/08\/11\/20160811-1b9956.jpg\" data-url=\"https:\/\/greenupload.com\/server7\/images\/2016\/08\/11\/20160811-1b9956.jpg\" class=\"bbImage \" loading=\"lazy\" style=\"\" width=\"\" height=\"\"> <\/a><br><a href=\"https:\/\/greenupload.com\/server7\/image\/J2kcvL\" target=\"_blank\" class=\"link link--external\" rel=\"nofollow ugc noopener\"> <img src=\"https:\/\/greenupload.com\/server7\/images\/2016\/08\/11\/20160811-204704.jpg\" data-url=\"https:\/\/greenupload.com\/server7\/images\/2016\/08\/11\/20160811-204704.jpg\" class=\"bbImage \" loading=\"lazy\" style=\"\" width=\"\" height=\"\"> <\/a><br><a href=\"https:\/\/greenupload.com\/server7\/image\/J2kgpD\" target=\"_blank\" class=\"link link--external\" rel=\"nofollow ugc noopener\"> <img src=\"https:\/\/greenupload.com\/server7\/images\/2016\/08\/11\/20160811-3df031.jpg\" data-url=\"https:\/\/greenupload.com\/server7\/images\/2016\/08\/11\/20160811-3df031.jpg\" class=\"bbImage \" loading=\"lazy\" style=\"\" width=\"\" height=\"\"> <\/a><br><a href=\"https:\/\/greenupload.com\/server7\/image\/J2kDji\" target=\"_blank\" class=\"link link--external\" rel=\"nofollow ugc noopener\"> <img src=\"https:\/\/greenupload.com\/server7\/images\/2016\/08\/11\/20160811-4dc9a7.jpg\" data-url=\"https:\/\/greenupload.com\/server7\/images\/2016\/08\/11\/20160811-4dc9a7.jpg\" class=\"bbImage \" loading=\"lazy\" style=\"\" width=\"\" height=\"\"> <\/a><br><a href=\"https:\/\/greenupload.com\/server7\/image\/J2kI6p\" target=\"_blank\" class=\"link link--external\" rel=\"nofollow ugc noopener\"> <img src=\"https:\/\/greenupload.com\/server7\/images\/2016\/08\/11\/20160811-582da1.jpg\" data-url=\"https:\/\/greenupload.com\/server7\/images\/2016\/08\/11\/20160811-582da1.jpg\" class=\"bbImage \" loading=\"lazy\" style=\"\" width=\"\" height=\"\"> <\/a><br><a href=\"https:\/\/greenupload.com\/server7\/image\/J2ktYU\" target=\"_blank\" class=\"link link--external\" rel=\"nofollow ugc noopener\"> <img src=\"https:\/\/greenupload.com\/server7\/images\/2016\/08\/11\/20160811-76f4be.jpg\" data-url=\"https:\/\/greenupload.com\/server7\/images\/2016\/08\/11\/20160811-76f4be.jpg\" class=\"bbImage \" loading=\"lazy\" style=\"\" width=\"\" height=\"\"> <\/a><br><a href=\"https:\/\/greenupload.com\/server7\/image\/J2kXXw\" target=\"_blank\" class=\"link link--external\" rel=\"nofollow ugc noopener\"> <img src=\"https:\/\/greenupload.com\/server7\/images\/2016\/08\/11\/20160811-10e1da5.jpg\" data-url=\"https:\/\/greenupload.com\/server7\/images\/2016\/08\/11\/20160811-10e1da5.jpg\" class=\"bbImage \" loading=\"lazy\" style=\"\" width=\"\" height=\"\"> <\/a><br><a href=\"https:\/\/greenupload.com\/server7\/image\/J2kaeH\" target=\"_blank\" class=\"link link--external\" rel=\"nofollow ugc noopener\"> <img src=\"https:\/\/greenupload.com\/server7\/images\/2016\/08\/11\/20160811-1109981.jpg\" data-url=\"https:\/\/greenupload.com\/server7\/images\/2016\/08\/11\/20160811-1109981.jpg\" class=\"bbImage \" loading=\"lazy\" style=\"\" width=\"\" height=\"\"> <\/a><br><a href=\"https:\/\/greenupload.com\/server7\/image\/J2kFPM\" target=\"_blank\" class=\"link link--external\" rel=\"nofollow ugc noopener\"> <img src=\"https:\/\/greenupload.com\/server7\/images\/2016\/08\/11\/20160811-12b78f2.jpg\" data-url=\"https:\/\/greenupload.com\/server7\/images\/2016\/08\/11\/20160811-12b78f2.jpg\" class=\"bbImage \" loading=\"lazy\" style=\"\" width=\"\" height=\"\"> <\/a><br><a href=\"https:\/\/greenupload.com\/server7\/image\/J2kMDn\" target=\"_blank\" class=\"link link--external\" rel=\"nofollow ugc noopener\"> <img src=\"https:\/\/greenupload.com\/server7\/images\/2016\/08\/11\/20160811-133fd8a.jpg\" data-url=\"https:\/\/greenupload.com\/server7\/images\/2016\/08\/11\/20160811-133fd8a.jpg\" class=\"bbImage \" loading=\"lazy\" style=\"\" width=\"\" height=\"\"> <\/a><br><a href=\"https:\/\/greenupload.com\/server7\/image\/J2kSpN\" target=\"_blank\" class=\"link link--external\" rel=\"nofollow ugc noopener\"> <img src=\"https:\/\/greenupload.com\/server7\/images\/2016\/08\/11\/20160811-1493bed.jpg\" data-url=\"https:\/\/greenupload.com\/server7\/images\/2016\/08\/11\/20160811-1493bed.jpg\" class=\"bbImage \" loading=\"lazy\" style=\"\" width=\"\" height=\"\"> <\/a>",
            "link_uuid": "0d09c3d8-be8e-4bc2-884f-0c5950593845",
            "post_id": "post-25787821",
            "status": "PROCESSED_NO_IMG",
            "download_links_status": "PROCESSED_NO_LINKS",
            "type": "MAIN_POST",
            "total_image": "0",
            "created_at": "2021-06-19 16:23:40"
        },
        {
            "uuid": "dbd08780-9c3f-4c5a-b05f-2bb0de1f5f9a",
            "author": "htman.dung",
            "content": "Ch\u00e0o c\u00e1c b\u00e1c, V\u1ee3 ch\u1ed3ng em chuy\u1ec3n ra n\u01b0\u1edbc ngo\u00e0i s\u1ed1ng g\u1ea7n 1 n\u0103m nay n\u00ean b\u00e2y gi\u1edd m\u1edbi post b\u00e0i l\u1ea1i. Ruby nh\u00e0 em x\u00e9t v\u1ec1 \u0111\u1ed9 d\u00e2m th\u00ec v\u00f4 \u0111\u1ed1i. Nay c\u00f3 c\u01a1 h\u1ed9i ti\u1ebfp x\u00fac v\u1edbi trai T\u00e2y th\u01b0\u1eddng xuy\u00ean, l\u1ea1i \u1edf m\u00f4i tr\u01b0\u1eddng c\u00f3 t\u01b0 t\u01b0\u1edfng tho\u00e1ng n\u00ean c\u00f3 th\u1ec3 x\u1ea3 ga sometho\u1ea3i m\u00e1i. M\u1ed7i l\u1ea7n Ruby l\u00e0m t\u00ecnh, em l\u1ea1i c\u00f3 c\u01a1 h\u1ed9i ch\u1ee5p v\u00e0i b\u1ed9 \u1ea3nh d\u00e2m \u0111\u00e3ng \u0111\u1ec3 t\u1eeb t\u1eeb khoe v\u1edbi c\u00e1c b\u00e1c. Em xin ra m\u1eaft t\u1eadp 1 gi\u1eefa Ruby v\u00e0 1 ban da tr\u1eafng c\u00f3 h\u00e0ng d\u00e0i b\u1ef1. C\u00e1c b\u00e1c c\u1ee9 comment tho\u1ea3i m\u00e1i cho v\u1ee3 ch\u1ed3ng em \u0111\u1ecdc nh\u00e9. B\u00e1c n\u00e0o mu\u1ed1n kik th\u00ec nh\u1eafn tin cho em.",
            "content_html": "<div class=\"bbWrapper\"> Ch\u00e0o c\u00e1c b\u00e1c, <br\/> <br\/> V\u1ee3 ch\u1ed3ng em chuy\u1ec3n ra n\u01b0\u1edbc ngo\u00e0i s\u1ed1ng g\u1ea7n 1 n\u0103m nay n\u00ean b\u00e2y gi\u1edd m\u1edbi post b\u00e0i l\u1ea1i. Ruby nh\u00e0 em x\u00e9t v\u1ec1 \u0111\u1ed9 d\u00e2m th\u00ec v\u00f4 \u0111\u1ed1i. Nay c\u00f3 c\u01a1 h\u1ed9i ti\u1ebfp x\u00fac v\u1edbi trai T\u00e2y th\u01b0\u1eddng xuy\u00ean, l\u1ea1i \u1edf m\u00f4i tr\u01b0\u1eddng c\u00f3 t\u01b0 t\u01b0\u1edfng tho\u00e1ng n\u00ean c\u00f3 th\u1ec3 x\u1ea3 ga sometho\u1ea3i m\u00e1i. M\u1ed7i l\u1ea7n Ruby l\u00e0m t\u00ecnh, em l\u1ea1i c\u00f3 c\u01a1 h\u1ed9i ch\u1ee5p v\u00e0i b\u1ed9 \u1ea3nh d\u00e2m \u0111\u00e3ng \u0111\u1ec3 t\u1eeb t\u1eeb khoe v\u1edbi c\u00e1c b\u00e1c. <br\/> <br\/> Em xin ra m\u1eaft t\u1eadp 1 gi\u1eefa Ruby v\u00e0 1 ban da tr\u1eafng c\u00f3 h\u00e0ng d\u00e0i b\u1ef1. C\u00e1c b\u00e1c c\u1ee9 comment tho\u1ea3i m\u00e1i cho v\u1ee3 ch\u1ed3ng em \u0111\u1ecdc nh\u00e9. B\u00e1c n\u00e0o mu\u1ed1n kik th\u00ec nh\u1eafn tin cho em. <br\/> <br\/> <a href=\"https:\/\/greenupload.com\/image\/med5S\" target=\"_blank\" class=\"link link--external\" rel=\"nofollow ugc noopener\"> <img src=\"https:\/\/greenupload.com\/images\/2018\/10\/10\/IMG_5439.jpg\" data-url=\"https:\/\/greenupload.com\/images\/2018\/10\/10\/IMG_5439.jpg\" class=\"bbImage \" loading=\"lazy\" style=\"\" width=\"\" height=\"\"\/> <\/a> <br\/> <br\/> <a href=\"https:\/\/greenupload.com\/image\/mexLV\" target=\"_blank\" class=\"link link--external\" rel=\"nofollow ugc noopener\"> <img src=\"https:\/\/greenupload.com\/images\/2018\/10\/10\/IMG_5434.jpg\" data-url=\"https:\/\/greenupload.com\/images\/2018\/10\/10\/IMG_5434.jpg\" class=\"bbImage \" loading=\"lazy\" style=\"\" width=\"\" height=\"\"\/> <\/a> <br\/> <br\/> <a href=\"https:\/\/greenupload.com\/image\/mea9M\" target=\"_blank\" class=\"link link--external\" rel=\"nofollow ugc noopener\"> <img src=\"https:\/\/greenupload.com\/images\/2018\/10\/10\/IMG_5446.jpg\" data-url=\"https:\/\/greenupload.com\/images\/2018\/10\/10\/IMG_5446.jpg\" class=\"bbImage \" loading=\"lazy\" style=\"\" width=\"\" height=\"\"\/> <\/a> <br\/> <br\/> <a href=\"https:\/\/greenupload.com\/image\/meGdU\" target=\"_blank\" class=\"link link--external\" rel=\"nofollow ugc noopener\"> <img src=\"https:\/\/greenupload.com\/images\/2018\/10\/10\/IMG_5427.jpg\" data-url=\"https:\/\/greenupload.com\/images\/2018\/10\/10\/IMG_5427.jpg\" class=\"bbImage \" loading=\"lazy\" style=\"\" width=\"\" height=\"\"\/> <\/a> <br\/> <br\/> <a href=\"https:\/\/greenupload.com\/image\/menIB\" target=\"_blank\" class=\"link link--external\" rel=\"nofollow ugc noopener\"> <img src=\"https:\/\/greenupload.com\/images\/2018\/10\/10\/IMG_5430.jpg\" data-url=\"https:\/\/greenupload.com\/images\/2018\/10\/10\/IMG_5430.jpg\" class=\"bbImage \" loading=\"lazy\" style=\"\" width=\"\" height=\"\"\/> <\/a> <br\/> <br\/> <a href=\"https:\/\/greenupload.com\/image\/meZD0\" target=\"_blank\" class=\"link link--external\" rel=\"nofollow ugc noopener\"> <img src=\"https:\/\/greenupload.com\/images\/2018\/10\/10\/IMG_5433.jpg\" data-url=\"https:\/\/greenupload.com\/images\/2018\/10\/10\/IMG_5433.jpg\" class=\"bbImage \" loading=\"lazy\" style=\"\" width=\"\" height=\"\"\/> <\/a> <br\/> <br\/> <a href=\"https:\/\/greenupload.com\/image\/mePZa\" target=\"_blank\" class=\"link link--external\" rel=\"nofollow ugc noopener\"> <img src=\"https:\/\/greenupload.com\/images\/2018\/10\/10\/IMG_5436.jpg\" data-url=\"https:\/\/greenupload.com\/images\/2018\/10\/10\/IMG_5436.jpg\" class=\"bbImage \" loading=\"lazy\" style=\"\" width=\"\" height=\"\"\/> <\/a> <\/div>",
            "link_uuid": "ab383755-c520-4569-9216-c946c9ce0e32",
            "post_id": "post-30310438",
            "status": "PROCESSED_NO_IMG",
            "download_links_status": "PROCESSED_NO_LINKS",
            "type": "MAIN_POST",
            "total_image": "0",
            "created_at": "2021-06-19 16:23:40"
        },
        {
            "uuid": "fcbadf20-e6b8-442e-9ebf-c6eed8abcce5",
            "author": "htman.dung",
            "content": "Ch\u00e0o c\u00e1c b\u00e1c, Sau khi post l\u00ean t\u1eadp 1 (https:\/\/thiendia88.com\/diendan\/thre...-lam-tinh-voi-trai-tay.1027323\/#post-25787821) \u0111\u01b0\u1ee3c c\u00e1c b\u00e1c \u1ee7ng h\u1ed9 th\u00ec t\u1ee5i em quy\u1ebft \u0111\u1ecbnh \u0111\u0103ng ti\u1ebfp t\u1eadp 2. L\u1ea7n n\u00e0y v\u1edbi 1 anh t\u00e2y kh\u00e1c m\u00e0 g\u1ea5u nh\u00e0 em g\u1eb7p \u0111\u01b0\u1ee3c \u1edf qu\u00e1n bar c\u00e1ch \u0111\u00e2y v\u00e0i tu\u1ea7n. Sau khi \u0111ang t\u1eadp 1 v\u00e0 nh\u1eadn \u0111\u01b0\u1ee3c th\u01b0 l\u00e0m quen c\u1ee7a c\u00e1c mem TD, t\u1ee5i em c\u0169ng \u0111\u00e3 some v\u1edbi 1 mem nh\u01b0ng v\u00ec l\u00ed do k\u00edn \u0111\u00e1o n\u00ean xin ph\u00e9p kh\u00f4ng \u0111\u0103ng h\u00ecnh. Mem n\u00e0y g\u1eedi 1 tin nh\u1eafn c\u00f3 mi\u00eau t\u1ea3 s\u1ebd l\u00e0m t\u00ecnh v\u1edbi G\u1ea5u nh\u01b0 th\u1ebf n\u00e0o n\u00ean G\u1ea5u r\u1ea5t kho\u00e1i (gi\u1ed1ng nh\u01b0 \u0111\u1ecdc truy\u1ec7n d\u00e2m ). C\u00f3 b\u00e1c n\u00e0o mu\u1ed1n l\u00e0m quen th\u00ec \u0111\u1ec3 l\u1ea1i tin nh\u1eafn \u1edf \u0111\u00e2y nh\u00e9. Sau khi g\u1eb7p \u1edf qu\u00e1n bar v\u00e0 t\u00e1n t\u1ec9nh nhau 1 h\u1ed3i, G\u1ea5u d\u1eabn trai t\u00e2y v\u1ec1 kh\u00e1ch s\u1ea1n tr\u01b0\u1edbc. L\u00fac em v\u00f4 t\u1edbi th\u00ec \u0111\u00e3 th\u1ea5y th\u1ebf n\u00e0y Trai t\u00e2y n\u00e0y ph\u1ea3i n\u00f3i l\u00e0 c\u00f3 h\u00e0ng thu\u1ed9c lo\u1ea1i r\u1ea5t b\u1ef1. G\u1ea5u b\u1eaft \u0111\u1ea7u tr\u1ed5 t\u00e0i th\u1ed5i k\u00e8n. Do h\u00e0ng h\u01a1i b\u1ef1 n\u00ean ch\u1eadt v\u1eadt 1 h\u1ed3i th\u00ec m\u1edbi nh\u00e9t v\u00f4 \u0111\u01b0\u1ee3c. L\u00fat c\u00e1n",
            "content_html": "Ch\u00e0o c\u00e1c b\u00e1c,<br><br>Sau khi post l\u00ean t\u1eadp 1 (<a href=\"https:\/\/thiendia88.com\/diendan\/threads\/gau-nha-u25-dam-dang-lam-tinh-voi-trai-tay.1027323\/#post-25787821\" class=\"link link--internal\">https:\/\/thiendia88.com\/diendan\/thre...-lam-tinh-voi-trai-tay.1027323\/#post-25787821<\/a>) \u0111\u01b0\u1ee3c c\u00e1c b\u00e1c \u1ee7ng h\u1ed9 th\u00ec t\u1ee5i em quy\u1ebft \u0111\u1ecbnh \u0111\u0103ng ti\u1ebfp t\u1eadp 2. L\u1ea7n n\u00e0y v\u1edbi 1 anh t\u00e2y kh\u00e1c m\u00e0 g\u1ea5u nh\u00e0 em g\u1eb7p \u0111\u01b0\u1ee3c \u1edf qu\u00e1n bar c\u00e1ch \u0111\u00e2y v\u00e0i tu\u1ea7n. <br><br>Sau khi \u0111ang t\u1eadp 1 v\u00e0 nh\u1eadn \u0111\u01b0\u1ee3c th\u01b0 l\u00e0m quen c\u1ee7a c\u00e1c mem TD, t\u1ee5i em c\u0169ng \u0111\u00e3 some v\u1edbi 1 mem nh\u01b0ng v\u00ec l\u00ed do k\u00edn \u0111\u00e1o n\u00ean xin ph\u00e9p kh\u00f4ng \u0111\u0103ng h\u00ecnh. Mem n\u00e0y g\u1eedi 1 tin nh\u1eafn c\u00f3 mi\u00eau t\u1ea3 s\u1ebd l\u00e0m t\u00ecnh v\u1edbi G\u1ea5u nh\u01b0 th\u1ebf n\u00e0o n\u00ean G\u1ea5u r\u1ea5t kho\u00e1i (gi\u1ed1ng nh\u01b0 \u0111\u1ecdc truy\u1ec7n d\u00e2m <img src=\"data:image\/gif;base64,R0lGODlhAQABAIAAAAAAAP\/\/\/yH5BAEAAAAALAAAAAABAAEAAAIBRAA7\" class=\"smilie smilie--sprite smilie--sprite8\" alt=\":D\" title=\"Big Grin :D\" loading=\"lazy\" data-shortname=\":D\">). C\u00f3 b\u00e1c n\u00e0o mu\u1ed1n l\u00e0m quen th\u00ec \u0111\u1ec3 l\u1ea1i tin nh\u1eafn \u1edf \u0111\u00e2y nh\u00e9. <br><br>Sau khi g\u1eb7p \u1edf qu\u00e1n bar v\u00e0 t\u00e1n t\u1ec9nh nhau 1 h\u1ed3i, G\u1ea5u d\u1eabn trai t\u00e2y v\u1ec1 kh\u00e1ch s\u1ea1n tr\u01b0\u1edbc. L\u00fac em v\u00f4 t\u1edbi th\u00ec \u0111\u00e3 th\u1ea5y th\u1ebf n\u00e0y<br><br> <script class=\"js-extraPhrases\" type=\"application\/json\"> { \"lightbox_close\": \"Close\", \"lightbox_next\": \"Next\", \"lightbox_previous\": \"Previous\", \"lightbox_error\": \"The requested content cannot be loaded. Please try again later.\", \"lightbox_start_slideshow\": \"Start slideshow\", \"lightbox_stop_slideshow\": \"Stop slideshow\", \"lightbox_full_screen\": \"Full screen\", \"lightbox_thumbnails\": \"Thumbnails\", \"lightbox_download\": \"Download\", \"lightbox_share\": \"Share\", \"lightbox_zoom\": \"Zoom\", \"lightbox_new_window\": \"New window\", \"lightbox_toggle_sidebar\": \"Toggle sidebar\" } <\/script> <div class=\"bbImageWrapper js-lbImage\" title=\"1367ada.jpg\" data-src=\"https:\/\/greenupload.com\/server7\/images\/2016\/09\/28\/1367ada.jpg\" data-lb-sidebar-href=\"\" data-lb-caption-extra-html=\"\" data-single-image=\"1\"> <img src=\"https:\/\/greenupload.com\/server7\/images\/2016\/09\/28\/1367ada.jpg\" data-url=\"https:\/\/greenupload.com\/server7\/images\/2016\/09\/28\/1367ada.jpg\" class=\"bbImage\" data-zoom-target=\"1\" style=\"\" alt=\"1367ada.jpg\" title=\"\" width=\"\" height=\"\" loading=\"lazy\"> <\/div> <br><br> <div class=\"bbImageWrapper js-lbImage\" title=\"1442ebb.jpg\" data-src=\"https:\/\/greenupload.com\/server7\/images\/2016\/09\/28\/1442ebb.jpg\" data-lb-sidebar-href=\"\" data-lb-caption-extra-html=\"\" data-single-image=\"1\"> <img src=\"https:\/\/greenupload.com\/server7\/images\/2016\/09\/28\/1442ebb.jpg\" data-url=\"https:\/\/greenupload.com\/server7\/images\/2016\/09\/28\/1442ebb.jpg\" class=\"bbImage\" data-zoom-target=\"1\" style=\"\" alt=\"1442ebb.jpg\" title=\"\" width=\"\" height=\"\" loading=\"lazy\"> <\/div> <br><br>Trai t\u00e2y n\u00e0y ph\u1ea3i n\u00f3i l\u00e0 c\u00f3 h\u00e0ng thu\u1ed9c lo\u1ea1i r\u1ea5t b\u1ef1. <br><br> <div class=\"bbImageWrapper js-lbImage\" title=\"91e881.jpg\" data-src=\"https:\/\/greenupload.com\/server7\/images\/2016\/09\/28\/91e881.jpg\" data-lb-sidebar-href=\"\" data-lb-caption-extra-html=\"\" data-single-image=\"1\"> <img src=\"https:\/\/greenupload.com\/server7\/images\/2016\/09\/28\/91e881.jpg\" data-url=\"https:\/\/greenupload.com\/server7\/images\/2016\/09\/28\/91e881.jpg\" class=\"bbImage\" data-zoom-target=\"1\" style=\"\" alt=\"91e881.jpg\" title=\"\" width=\"\" height=\"\" loading=\"lazy\"> <\/div> <br><br>G\u1ea5u b\u1eaft \u0111\u1ea7u tr\u1ed5 t\u00e0i th\u1ed5i k\u00e8n.<br><br> <div class=\"bbImageWrapper js-lbImage\" title=\"IMG_0766f97f7.jpg\" data-src=\"https:\/\/greenupload.com\/server7\/images\/2016\/09\/28\/IMG_0766f97f7.jpg\" data-lb-sidebar-href=\"\" data-lb-caption-extra-html=\"\" data-single-image=\"1\"> <img src=\"https:\/\/greenupload.com\/server7\/images\/2016\/09\/28\/IMG_0766f97f7.jpg\" data-url=\"https:\/\/greenupload.com\/server7\/images\/2016\/09\/28\/IMG_0766f97f7.jpg\" class=\"bbImage\" data-zoom-target=\"1\" style=\"\" alt=\"IMG_0766f97f7.jpg\" title=\"\" width=\"\" height=\"\" loading=\"lazy\"> <\/div> <br> <div class=\"bbImageWrapper js-lbImage\" title=\"IMG_0769a38d2.jpg\" data-src=\"https:\/\/greenupload.com\/server7\/images\/2016\/09\/28\/IMG_0769a38d2.jpg\" data-lb-sidebar-href=\"\" data-lb-caption-extra-html=\"\" data-single-image=\"1\"> <img src=\"https:\/\/greenupload.com\/server7\/images\/2016\/09\/28\/IMG_0769a38d2.jpg\" data-url=\"https:\/\/greenupload.com\/server7\/images\/2016\/09\/28\/IMG_0769a38d2.jpg\" class=\"bbImage\" data-zoom-target=\"1\" style=\"\" alt=\"IMG_0769a38d2.jpg\" title=\"\" width=\"\" height=\"\" loading=\"lazy\"> <\/div> <br> <div class=\"bbImageWrapper js-lbImage\" title=\"IMG_07707b64b.jpg\" data-src=\"https:\/\/greenupload.com\/server7\/images\/2016\/09\/28\/IMG_07707b64b.jpg\" data-lb-sidebar-href=\"\" data-lb-caption-extra-html=\"\" data-single-image=\"1\"> <img src=\"https:\/\/greenupload.com\/server7\/images\/2016\/09\/28\/IMG_07707b64b.jpg\" data-url=\"https:\/\/greenupload.com\/server7\/images\/2016\/09\/28\/IMG_07707b64b.jpg\" class=\"bbImage\" data-zoom-target=\"1\" style=\"\" alt=\"IMG_07707b64b.jpg\" title=\"\" width=\"\" height=\"\" loading=\"lazy\"> <\/div> <br> <div class=\"bbImageWrapper js-lbImage\" title=\"IMG_07738dcc9.jpg\" data-src=\"https:\/\/greenupload.com\/server7\/images\/2016\/09\/28\/IMG_07738dcc9.jpg\" data-lb-sidebar-href=\"\" data-lb-caption-extra-html=\"\" data-single-image=\"1\"> <img src=\"https:\/\/greenupload.com\/server7\/images\/2016\/09\/28\/IMG_07738dcc9.jpg\" data-url=\"https:\/\/greenupload.com\/server7\/images\/2016\/09\/28\/IMG_07738dcc9.jpg\" class=\"bbImage\" data-zoom-target=\"1\" style=\"\" alt=\"IMG_07738dcc9.jpg\" title=\"\" width=\"\" height=\"\" loading=\"lazy\"> <\/div> <br><br>Do h\u00e0ng h\u01a1i b\u1ef1 n\u00ean ch\u1eadt v\u1eadt 1 h\u1ed3i th\u00ec m\u1edbi nh\u00e9t v\u00f4 \u0111\u01b0\u1ee3c.<br><br> <div class=\"bbImageWrapper js-lbImage\" title=\"494e79.jpg\" data-src=\"https:\/\/greenupload.com\/server7\/images\/2016\/09\/28\/494e79.jpg\" data-lb-sidebar-href=\"\" data-lb-caption-extra-html=\"\" data-single-image=\"1\"> <img src=\"https:\/\/greenupload.com\/server7\/images\/2016\/09\/28\/494e79.jpg\" data-url=\"https:\/\/greenupload.com\/server7\/images\/2016\/09\/28\/494e79.jpg\" class=\"bbImage\" data-zoom-target=\"1\" style=\"\" alt=\"494e79.jpg\" title=\"\" width=\"\" height=\"\" loading=\"lazy\"> <\/div> <br> <div class=\"bbImageWrapper js-lbImage\" title=\"130618.jpg\" data-src=\"https:\/\/greenupload.com\/server7\/images\/2016\/09\/28\/130618.jpg\" data-lb-sidebar-href=\"\" data-lb-caption-extra-html=\"\" data-single-image=\"1\"> <img src=\"https:\/\/greenupload.com\/server7\/images\/2016\/09\/28\/130618.jpg\" data-url=\"https:\/\/greenupload.com\/server7\/images\/2016\/09\/28\/130618.jpg\" class=\"bbImage\" data-zoom-target=\"1\" style=\"\" alt=\"130618.jpg\" title=\"\" width=\"\" height=\"\" loading=\"lazy\"> <\/div> <br> <div class=\"bbImageWrapper js-lbImage\" title=\"212d6e.jpg\" data-src=\"https:\/\/greenupload.com\/server7\/images\/2016\/09\/28\/212d6e.jpg\" data-lb-sidebar-href=\"\" data-lb-caption-extra-html=\"\" data-single-image=\"1\"> <img src=\"https:\/\/greenupload.com\/server7\/images\/2016\/09\/28\/212d6e.jpg\" data-url=\"https:\/\/greenupload.com\/server7\/images\/2016\/09\/28\/212d6e.jpg\" class=\"bbImage\" data-zoom-target=\"1\" style=\"\" alt=\"212d6e.jpg\" title=\"\" width=\"\" height=\"\" loading=\"lazy\"> <\/div> <br> <div class=\"bbImageWrapper js-lbImage\" title=\"IMG_0778121f2.jpg\" data-src=\"https:\/\/greenupload.com\/server7\/images\/2016\/09\/28\/IMG_0778121f2.jpg\" data-lb-sidebar-href=\"\" data-lb-caption-extra-html=\"\" data-single-image=\"1\"> <img src=\"https:\/\/greenupload.com\/server7\/images\/2016\/09\/28\/IMG_0778121f2.jpg\" data-url=\"https:\/\/greenupload.com\/server7\/images\/2016\/09\/28\/IMG_0778121f2.jpg\" class=\"bbImage\" data-zoom-target=\"1\" style=\"\" alt=\"IMG_0778121f2.jpg\" title=\"\" width=\"\" height=\"\" loading=\"lazy\"> <\/div> <br><br>L\u00fat c\u00e1n<br><br> <div class=\"bbImageWrapper js-lbImage\" title=\"56bd91.jpg\" data-src=\"https:\/\/greenupload.com\/server7\/images\/2016\/09\/28\/56bd91.jpg\" data-lb-sidebar-href=\"\" data-lb-caption-extra-html=\"\" data-single-image=\"1\"> <img src=\"https:\/\/greenupload.com\/server7\/images\/2016\/09\/28\/56bd91.jpg\" data-url=\"https:\/\/greenupload.com\/server7\/images\/2016\/09\/28\/56bd91.jpg\" class=\"bbImage\" data-zoom-target=\"1\" style=\"\" alt=\"56bd91.jpg\" title=\"\" width=\"\" height=\"\" loading=\"lazy\"> <\/div> <br> <div class=\"bbImageWrapper js-lbImage\" title=\"6b6944.jpg\" data-src=\"https:\/\/greenupload.com\/server7\/images\/2016\/09\/28\/6b6944.jpg\" data-lb-sidebar-href=\"\" data-lb-caption-extra-html=\"\" data-single-image=\"1\"> <img src=\"https:\/\/greenupload.com\/server7\/images\/2016\/09\/28\/6b6944.jpg\" data-url=\"https:\/\/greenupload.com\/server7\/images\/2016\/09\/28\/6b6944.jpg\" class=\"bbImage\" data-zoom-target=\"1\" style=\"\" alt=\"6b6944.jpg\" title=\"\" width=\"\" height=\"\" loading=\"lazy\"> <\/div>",
            "link_uuid": "ce7aa85b-443e-43eb-9204-cd922ad6d706",
            "post_id": "post-26182372",
            "status": "PROCESSED_NO_IMG",
            "download_links_status": "PROCESSED_NO_LINKS",
            "type": "MAIN_POST",
            "total_image": "0",
            "created_at": "2021-06-19 16:23:40"
        }
    ],
    "images": [
        "https:\/\/greenupload.com\/images\/2018\/11\/18\/IMG_4608-2-9.jpg",
        "https:\/\/greenupload.com\/images\/2018\/11\/18\/IMG_4605-2-7.jpg",
        "https:\/\/greenupload.com\/images\/2018\/11\/18\/IMG_4611-2-11.jpg",
        "https:\/\/greenupload.com\/images\/2018\/11\/18\/IMG_4610-2-10.jpg",
        "https:\/\/greenupload.com\/images\/2018\/11\/18\/IMG_4612-2-12.jpg",
        "https:\/\/greenupload.com\/images\/2018\/11\/18\/IMG_4606-2-8.jpg",
        "https:\/\/greenupload.com\/images\/2021\/01\/15\/IMG_20210115_152951.jpg",
        "https:\/\/greenupload.com\/images\/2021\/01\/15\/IMG_20210115_153249.jpg",
        "https:\/\/greenupload.com\/images\/2021\/01\/15\/IMG_20210115_153032.jpg",
        "https:\/\/greenupload.com\/images\/2021\/01\/15\/Screenshot_20210115_153706.jpg",
        "https:\/\/greenupload.com\/images\/2021\/01\/15\/Screenshot_20210115_153611.jpg",
        "https:\/\/greenupload.com\/images\/2021\/01\/15\/IMG_20210115_153321.jpg",
        "https:\/\/greenupload.com\/images\/2021\/01\/15\/IMG_20210115_153213.jpg",
        "https:\/\/greenupload.com\/images\/2021\/01\/15\/IMG_20210115_152927.jpg",
        "https:\/\/greenupload.com\/images\/2021\/01\/15\/Screenshot_20210115_153724.jpg",
        "https:\/\/greenupload.com\/server7\/images\/2016\/08\/11\/20160811-204704.jpg",
        "https:\/\/greenupload.com\/server7\/images\/2016\/08\/11\/20160811-582da1.jpg",
        "https:\/\/greenupload.com\/server7\/images\/2016\/08\/11\/20160811-1493bed.jpg",
        "https:\/\/greenupload.com\/server7\/images\/2016\/08\/11\/20160811-1b9956.jpg",
        "https:\/\/greenupload.com\/server7\/images\/2016\/08\/11\/20160811-4dc9a7.jpg",
        "https:\/\/greenupload.com\/server7\/images\/2016\/08\/11\/20160811-10e1da5.jpg",
        "https:\/\/greenupload.com\/server7\/images\/2016\/08\/11\/20160811-12b78f2.jpg",
        "https:\/\/greenupload.com\/server7\/images\/2016\/08\/11\/20160811-133fd8a.jpg",
        "https:\/\/greenupload.com\/server7\/images\/2016\/08\/11\/20160811-76f4be.jpg",
        "https:\/\/greenupload.com\/server7\/images\/2016\/08\/11\/20160811-3df031.jpg",
        "https:\/\/greenupload.com\/server7\/images\/2016\/08\/11\/20160811-1109981.jpg",
        "https:\/\/greenupload.com\/server7\/images\/2016\/08\/11\/20160811-96d441.jpg",
        "https:\/\/greenupload.com\/images\/2018\/10\/10\/IMG_5439.jpg",
        "https:\/\/greenupload.com\/images\/2018\/10\/10\/IMG_5434.jpg",
        "https:\/\/greenupload.com\/images\/2018\/10\/10\/IMG_5436.jpg",
        "https:\/\/greenupload.com\/images\/2018\/10\/10\/IMG_5427.jpg",
        "https:\/\/greenupload.com\/images\/2018\/10\/10\/IMG_5446.jpg",
        "https:\/\/greenupload.com\/images\/2018\/10\/10\/IMG_5433.jpg",
        "https:\/\/greenupload.com\/images\/2018\/10\/10\/IMG_5430.jpg",
        "https:\/\/greenupload.com\/server7\/images\/2016\/09\/28\/IMG_07707b64b.jpg",
        "https:\/\/greenupload.com\/server7\/images\/2016\/09\/28\/IMG_07738dcc9.jpg",
        "https:\/\/greenupload.com\/server7\/images\/2016\/09\/28\/130618.jpg",
        "https:\/\/greenupload.com\/server7\/images\/2016\/09\/28\/IMG_0778121f2.jpg",
        "https:\/\/greenupload.com\/server7\/images\/2016\/09\/28\/6b6944.jpg",
        "https:\/\/greenupload.com\/server7\/images\/2016\/09\/28\/494e79.jpg",
        "https:\/\/greenupload.com\/server7\/images\/2016\/09\/28\/IMG_0769a38d2.jpg",
        "https:\/\/greenupload.com\/server7\/images\/2016\/09\/28\/1442ebb.jpg",
        "https:\/\/greenupload.com\/server7\/images\/2016\/09\/28\/91e881.jpg",
        "https:\/\/greenupload.com\/server7\/images\/2016\/09\/28\/IMG_0766f97f7.jpg",
        "https:\/\/greenupload.com\/server7\/images\/2016\/09\/28\/1367ada.jpg",
        "https:\/\/greenupload.com\/server7\/images\/2016\/09\/28\/56bd91.jpg",
        "https:\/\/greenupload.com\/server7\/images\/2016\/09\/28\/212d6e.jpg"
    ]
}