[
    {
        "uuid": "160216f2-7451-4cb7-93c2-a2e5cb582920",
        "author": "mitdactn",
        "content": "Em N\u00e0y Cho C\u00e1c B\u00e1c Ph\u00e1n Gi\u00e1!Share cho AE L\u1ecbch S\u1ef1. \u0110\u1eb6t G\u1ea1ch N\u00e0o!!!",
        "content_html": "<span style=\"font-size: 26px\"><span style=\"color: Red\"><span style=\"color: Yellow\">Em N\u00e0y Cho C\u00e1c B\u00e1c Ph\u00e1n Gi\u00e1!<br>Share cho AE L\u1ecbch S\u1ef1. \u0110\u1eb6t G\u1ea1ch N\u00e0o!!!<\/span><br><\/span><\/span><br> <a href=\"http:\/\/server5.upload69.net\/\" target=\"_blank\" class=\"link link--external\" rel=\"nofollow ugc noopener\"> <img src=\"https:\/\/greenupload.com\/server5\/images\/77669382792531650837.jpg\" data-url=\"https:\/\/greenupload.com\/server5\/images\/77669382792531650837.jpg\" class=\"bbImage \" loading=\"lazy\" style=\"\" width=\"\" height=\"\"> <\/a><br> <a href=\"http:\/\/server5.upload69.net\/\" target=\"_blank\" class=\"link link--external\" rel=\"nofollow ugc noopener\"> <img src=\"https:\/\/greenupload.com\/server5\/images\/73872627449874039475.jpg\" data-url=\"https:\/\/greenupload.com\/server5\/images\/73872627449874039475.jpg\" class=\"bbImage \" loading=\"lazy\" style=\"\" width=\"\" height=\"\"> <\/a><br> <a href=\"http:\/\/server5.upload69.net\/\" target=\"_blank\" class=\"link link--external\" rel=\"nofollow ugc noopener\"> <img src=\"https:\/\/greenupload.com\/server5\/images\/76950655369649715130.jpg\" data-url=\"https:\/\/greenupload.com\/server5\/images\/76950655369649715130.jpg\" class=\"bbImage \" loading=\"lazy\" style=\"\" width=\"\" height=\"\"> <\/a><br> <a href=\"http:\/\/server5.upload69.net\/\" target=\"_blank\" class=\"link link--external\" rel=\"nofollow ugc noopener\"> <img src=\"https:\/\/greenupload.com\/server5\/images\/81758731817344422164.jpg\" data-url=\"https:\/\/greenupload.com\/server5\/images\/81758731817344422164.jpg\" class=\"bbImage \" loading=\"lazy\" style=\"\" width=\"\" height=\"\"> <\/a><br> <a href=\"http:\/\/server5.upload69.net\/\" target=\"_blank\" class=\"link link--external\" rel=\"nofollow ugc noopener\"> <img src=\"https:\/\/greenupload.com\/server5\/images\/21481848387938868471.jpg\" data-url=\"https:\/\/greenupload.com\/server5\/images\/21481848387938868471.jpg\" class=\"bbImage \" loading=\"lazy\" style=\"\" width=\"\" height=\"\"> <\/a><br> <a href=\"http:\/\/server5.upload69.net\/\" target=\"_blank\" class=\"link link--external\" rel=\"nofollow ugc noopener\"> <img src=\"https:\/\/greenupload.com\/server5\/images\/64249269205389317884.jpg\" data-url=\"https:\/\/greenupload.com\/server5\/images\/64249269205389317884.jpg\" class=\"bbImage \" loading=\"lazy\" style=\"\" width=\"\" height=\"\"> <\/a><br> <a href=\"http:\/\/server5.upload69.net\/\" target=\"_blank\" class=\"link link--external\" rel=\"nofollow ugc noopener\"> <img src=\"https:\/\/greenupload.com\/server5\/images\/66445211684301688341.jpg\" data-url=\"https:\/\/greenupload.com\/server5\/images\/66445211684301688341.jpg\" class=\"bbImage \" loading=\"lazy\" style=\"\" width=\"\" height=\"\"> <\/a><br><br> <a href=\"http:\/\/server5.upload69.net\/\" target=\"_blank\" class=\"link link--external\" rel=\"nofollow ugc noopener\"> <img src=\"https:\/\/greenupload.com\/server5\/images\/41197777866066934866.jpg\" data-url=\"https:\/\/greenupload.com\/server5\/images\/41197777866066934866.jpg\" class=\"bbImage \" loading=\"lazy\" style=\"\" width=\"\" height=\"\"> <\/a><br> <a href=\"http:\/\/server5.upload69.net\/\" target=\"_blank\" class=\"link link--external\" rel=\"nofollow ugc noopener\"> <img src=\"https:\/\/greenupload.com\/server5\/images\/27411453030990092056.jpg\" data-url=\"https:\/\/greenupload.com\/server5\/images\/27411453030990092056.jpg\" class=\"bbImage \" loading=\"lazy\" style=\"\" width=\"\" height=\"\"> <\/a><br> <a href=\"http:\/\/server5.upload69.net\/\" target=\"_blank\" class=\"link link--external\" rel=\"nofollow ugc noopener\"> <img src=\"https:\/\/greenupload.com\/server5\/images\/44900646576702620383.jpg\" data-url=\"https:\/\/greenupload.com\/server5\/images\/44900646576702620383.jpg\" class=\"bbImage \" loading=\"lazy\" style=\"\" width=\"\" height=\"\"> <\/a><br> <a href=\"http:\/\/server5.upload69.net\/\" target=\"_blank\" class=\"link link--external\" rel=\"nofollow ugc noopener\"> <img src=\"https:\/\/greenupload.com\/server5\/images\/91094018443723810151.jpg\" data-url=\"https:\/\/greenupload.com\/server5\/images\/91094018443723810151.jpg\" class=\"bbImage \" loading=\"lazy\" style=\"\" width=\"\" height=\"\"> <\/a><br> <a href=\"http:\/\/server5.upload69.net\/\" target=\"_blank\" class=\"link link--external\" rel=\"nofollow ugc noopener\"> <img src=\"https:\/\/greenupload.com\/server5\/images\/96033736625853616550.jpg\" data-url=\"https:\/\/greenupload.com\/server5\/images\/96033736625853616550.jpg\" class=\"bbImage \" loading=\"lazy\" style=\"\" width=\"\" height=\"\"> <\/a><br> <a href=\"http:\/\/server5.upload69.net\/\" target=\"_blank\" class=\"link link--external\" rel=\"nofollow ugc noopener\"> <img src=\"https:\/\/greenupload.com\/server5\/images\/17061946518491552045.jpg\" data-url=\"https:\/\/greenupload.com\/server5\/images\/17061946518491552045.jpg\" class=\"bbImage \" loading=\"lazy\" style=\"\" width=\"\" height=\"\"> <\/a><br> <a href=\"http:\/\/server5.upload69.net\/\" target=\"_blank\" class=\"link link--external\" rel=\"nofollow ugc noopener\"> <img src=\"https:\/\/greenupload.com\/server5\/images\/04823145486705227563.jpg\" data-url=\"https:\/\/greenupload.com\/server5\/images\/04823145486705227563.jpg\" class=\"bbImage \" loading=\"lazy\" style=\"\" width=\"\" height=\"\"> <\/a>",
        "link_uuid": "f56975ab-f827-4bce-9a45-5aa6707e207b",
        "post_id": "post-6590139",
        "status": "PROCESSED",
        "type": "MAIN_POST",
        "total_image": "14",
        "created_at": "2021-06-19 16:23:40"
    }
]